{
  "TBTOOL_VIP_1D_A7K2M9X4": {"type": "1D", "description": "Key VIP 1 ngày"},
  "TBTOOL_VIP_1D_B3X8P4W1": {"type": "1D", "description": "Key VIP 1 ngày"},
  "TBTOOL_VIP_1D_C5R6W1Y9": {"type": "1D", "description": "Key VIP 1 ngày"},
  "TBTOOL_VIP_1D_D9J2L7V3": {"type": "1D", "description": "Key VIP 1 ngày"},
  "TBTOOL_VIP_1D_E4N8T3Z6": {"type": "1D", "description": "Key VIP 1 ngày"},
  "TBTOOL_VIP_1D_F6K1M9A2": {"type": "1D", "description": "Key VIP 1 ngày"},
  "TBTOOL_VIP_1D_G2H5P8Q7": {"type": "1D", "description": "Key VIP 1 ngày"},
  "TBTOOL_VIP_1D_H7R3W6E1": {"type": "1D", "description": "Key VIP 1 ngày"},
  "TBTOOL_VIP_1D_J9L1X4C5": {"type": "1D", "description": "Key VIP 1 ngày"},
  "TBTOOL_VIP_1D_K5Q8Z2F3": {"type": "1D", "description": "Key VIP 1 ngày"},
  "TBTOOL_VIP_1D_M4N6P8S9": {"type": "1D", "description": "Key VIP 1 ngày"},
  "TBTOOL_VIP_1D_Q1R3T5U7": {"type": "1D", "description": "Key VIP 1 ngày"},
  "TBTOOL_VIP_1D_W2X4Y6Z8": {"type": "1D", "description": "Key VIP 1 ngày"},
  "TBTOOL_VIP_1D_A9B1C3D5": {"type": "1D", "description": "Key VIP 1 ngày"},
  "TBTOOL_VIP_1D_E7F2G4H6": {"type": "1D", "description": "Key VIP 1 ngày"},
  "TBTOOL_VIP_1D_I8J3K5L7": {"type": "1D", "description": "Key VIP 1 ngày"},
  "TBTOOL_VIP_1D_M9N1O2P4": {"type": "1D", "description": "Key VIP 1 ngày"},
  "TBTOOL_VIP_1D_Q6R8S3T5": {"type": "1D", "description": "Key VIP 1 ngày"},
  "TBTOOL_VIP_1D_U7V9W2X4": {"type": "1D", "description": "Key VIP 1 ngày"},
  "TBTOOL_VIP_1D_Y8Z1A3B6": {"type": "1D", "description": "Key VIP 1 ngày"},
  "TBTOOL_VIP_1D_C4D6E8F9": {"type": "1D", "description": "Key VIP 1 ngày"},
  "TBTOOL_VIP_1D_G1H3I5J7": {"type": "1D", "description": "Key VIP 1 ngày"},
  "TBTOOL_VIP_1D_K2L4M6N8": {"type": "1D", "description": "Key VIP 1 ngày"},
  "TBTOOL_VIP_1D_O9P1Q3R5": {"type": "1D", "description": "Key VIP 1 ngày"},
  "TBTOOL_VIP_1D_S7T2U4V6": {"type": "1D", "description": "Key VIP 1 ngày"},
  "TBTOOL_VIP_1D_W8X3Y5Z7": {"type": "1D", "description": "Key VIP 1 ngày"},
  "TBTOOL_VIP_1D_A2B4C6D8": {"type": "1D", "description": "Key VIP 1 ngày"},
  "TBTOOL_VIP_1D_E9F1G3H5": {"type": "1D", "description": "Key VIP 1 ngày"},
  "TBTOOL_VIP_1D_I7J2K4L6": {"type": "1D", "description": "Key VIP 1 ngày"},
  "TBTOOL_VIP_1D_M8N3O5P7": {"type": "1D", "description": "Key VIP 1 ngày"},
  "TBTOOL_VIP_1D_Q9R4S6T8": {"type": "1D", "description": "Key VIP 1 ngày"},
  "TBTOOL_VIP_1D_U1V3W5X7": {"type": "1D", "description": "Key VIP 1 ngày"},
  "TBTOOL_VIP_1D_Y2Z4A6B8": {"type": "1D", "description": "Key VIP 1 ngày"},
  "TBTOOL_VIP_1D_C9D1E3F5": {"type": "1D", "description": "Key VIP 1 ngày"},
  "TBTOOL_VIP_1D_G7H2I4J6": {"type": "1D", "description": "Key VIP 1 ngày"},
  "TBTOOL_VIP_1D_K8L3M5N7": {"type": "1D", "description": "Key VIP 1 ngày"},
  "TBTOOL_VIP_1D_O9P4Q6R8": {"type": "1D", "description": "Key VIP 1 ngày"},
  "TBTOOL_VIP_1D_S1T3U5V7": {"type": "1D", "description": "Key VIP 1 ngày"},
  "TBTOOL_VIP_1D_W2X4Y6Z8": {"type": "1D", "description": "Key VIP 1 ngày"},
  "TBTOOL_VIP_1D_A9B1C3D5": {"type": "1D", "description": "Key VIP 1 ngày"},
  "TBTOOL_VIP_1D_E7F2G4H6": {"type": "1D", "description": "Key VIP 1 ngày"},
  "TBTOOL_VIP_1D_I8J3K5L7": {"type": "1D", "description": "Key VIP 1 ngày"},
  "TBTOOL_VIP_1D_M9N1O2P4": {"type": "1D", "description": "Key VIP 1 ngày"},
  "TBTOOL_VIP_1D_Q6R8S3T5": {"type": "1D", "description": "Key VIP 1 ngày"},
  "TBTOOL_VIP_1D_U7V9W2X4": {"type": "1D", "description": "Key VIP 1 ngày"},
  "TBTOOL_VIP_1D_Y8Z1A3B6": {"type": "1D", "description": "Key VIP 1 ngày"},
  "TBTOOL_VIP_1D_C4D6E8F9": {"type": "1D", "description": "Key VIP 1 ngày"},
  "TBTOOL_VIP_1D_G1H3I5J7": {"type": "1D", "description": "Key VIP 1 ngày"},
  "TBTOOL_VIP_1D_K2L4M6N8": {"type": "1D", "description": "Key VIP 1 ngày"},
  "TBTOOL_VIP_1D_O9P1Q3R5": {"type": "1D", "description": "Key VIP 1 ngày"},
  "TBTOOL_VIP_1D_S7T2U4V6": {"type": "1D", "description": "Key VIP 1 ngày"},
  "TBTOOL_VIP_1D_W8X3Y5Z7": {"type": "1D", "description": "Key VIP 1 ngày"},
  "TBTOOL_VIP_1D_A2B4C6D8": {"type": "1D", "description": "Key VIP 1 ngày"},
  "TBTOOL_VIP_1D_E9F1G3H5": {"type": "1D", "description": "Key VIP 1 ngày"},
  "TBTOOL_VIP_1D_I7J2K4L6": {"type": "1D", "description": "Key VIP 1 ngày"},
  "TBTOOL_VIP_1D_M8N3O5P7": {"type": "1D", "description": "Key VIP 1 ngày"},
  "TBTOOL_VIP_1D_Q9R4S6T8": {"type": "1D", "description": "Key VIP 1 ngày"},
  "TBTOOL_VIP_1D_U1V3W5X7": {"type": "1D", "description": "Key VIP 1 ngày"},
  "TBTOOL_VIP_1D_Y2Z4A6B8": {"type": "1D", "description": "Key VIP 1 ngày"},
  "TBTOOL_VIP_1D_C9D1E3F5": {"type": "1D", "description": "Key VIP 1 ngày"},
  "TBTOOL_VIP_1D_G7H2I4J6": {"type": "1D", "description": "Key VIP 1 ngày"},
  "TBTOOL_VIP_1D_K8L3M5N7": {"type": "1D", "description": "Key VIP 1 ngày"},
  "TBTOOL_VIP_1D_O9P4Q6R8": {"type": "1D", "description": "Key VIP 1 ngày"},
  "TBTOOL_VIP_1D_S1T3U5V7": {"type": "1D", "description": "Key VIP 1 ngày"},
  "TBTOOL_VIP_1D_W2X4Y6Z8": {"type": "1D", "description": "Key VIP 1 ngày"},
  "TBTOOL_VIP_1D_A9B1C3D5": {"type": "1D", "description": "Key VIP 1 ngày"},
  "TBTOOL_VIP_1D_E7F2G4H6": {"type": "1D", "description": "Key VIP 1 ngày"},
  "TBTOOL_VIP_1D_I8J3K5L7": {"type": "1D", "description": "Key VIP 1 ngày"},
  "TBTOOL_VIP_1D_M9N1O2P4": {"type": "1D", "description": "Key VIP 1 ngày"},
  "TBTOOL_VIP_1D_Q6R8S3T5": {"type": "1D", "description": "Key VIP 1 ngày"},
  "TBTOOL_VIP_1D_U7V9W2X4": {"type": "1D", "description": "Key VIP 1 ngày"},
  "TBTOOL_VIP_1D_Y8Z1A3B6": {"type": "1D", "description": "Key VIP 1 ngày"},
  "TBTOOL_VIP_1D_C4D6E8F9": {"type": "1D", "description": "Key VIP 1 ngày"},
  "TBTOOL_VIP_1D_G1H3I5J7": {"type": "1D", "description": "Key VIP 1 ngày"},
  "TBTOOL_VIP_1D_K2L4M6N8": {"type": "1D", "description": "Key VIP 1 ngày"},
  "TBTOOL_VIP_1D_O9P1Q3R5": {"type": "1D", "description": "Key VIP 1 ngày"},
  "TBTOOL_VIP_1D_S7T2U4V6": {"type": "1D", "description": "Key VIP 1 ngày"},
  "TBTOOL_VIP_1D_W8X3Y5Z7": {"type": "1D", "description": "Key VIP 1 ngày"},
  "TBTOOL_VIP_1D_A2B4C6D8": {"type": "1D", "description": "Key VIP 1 ngày"},
  "TBTOOL_VIP_1D_E9F1G3H5": {"type": "1D", "description": "Key VIP 1 ngày"},
  "TBTOOL_VIP_1D_I7J2K4L6": {"type": "1D", "description": "Key VIP 1 ngày"},
  "TBTOOL_VIP_1D_M8N3O5P7": {"type": "1D", "description": "Key VIP 1 ngày"},
  "TBTOOL_VIP_1D_Q9R4S6T8": {"type": "1D", "description": "Key VIP 1 ngày"},
  "TBTOOL_VIP_1D_U1V3W5X7": {"type": "1D", "description": "Key VIP 1 ngày"},
  "TBTOOL_VIP_1D_Y2Z4A6B8": {"type": "1D", "description": "Key VIP 1 ngày"},
  "TBTOOL_VIP_1D_C9D1E3F5": {"type": "1D", "description": "Key VIP 1 ngày"},
  "TBTOOL_VIP_1D_G7H2I4J6": {"type": "1D", "description": "Key VIP 1 ngày"},
  "TBTOOL_VIP_1D_K8L3M5N7": {"type": "1D", "description": "Key VIP 1 ngày"},
  "TBTOOL_VIP_1D_O9P4Q6R8": {"type": "1D", "description": "Key VIP 1 ngày"},
  "TBTOOL_VIP_1D_S1T3U5V7": {"type": "1D", "description": "Key VIP 1 ngày"},
  "TBTOOL_VIP_1D_W2X4Y6Z8": {"type": "1D", "description": "Key VIP 1 ngày"},
  "TBTOOL_VIP_1D_A9B1C3D5": {"type": "1D", "description": "Key VIP 1 ngày"},
  "TBTOOL_VIP_1D_E7F2G4H6": {"type": "1D", "description": "Key VIP 1 ngày"},
  "TBTOOL_VIP_1D_I8J3K5L7": {"type": "1D", "description": "Key VIP 1 ngày"},
  "TBTOOL_VIP_1D_M9N1O2P4": {"type": "1D", "description": "Key VIP 1 ngày"},
  "TBTOOL_VIP_1D_Q6R8S3T5": {"type": "1D", "description": "Key VIP 1 ngày"},
  "TBTOOL_VIP_1D_U7V9W2X4": {"type": "1D", "description": "Key VIP 1 ngày"},
  "TBTOOL_VIP_1D_Y8Z1A3B6": {"type": "1D", "description": "Key VIP 1 ngày"},
  "TBTOOL_VIP_1D_C4D6E8F9": {"type": "1D", "description": "Key VIP 1 ngày"},
  "TBTOOL_VIP_1D_G1H3I5J7": {"type": "1D", "description": "Key VIP 1 ngày"},

  "TBTOOL_VIP_3D_X9B4R7M2": {"type": "3D", "description": "Key VIP 3 ngày"},
  "TBTOOL_VIP_3D_Y2T8G3N5": {"type": "3D", "description": "Key VIP 3 ngày"},
  "TBTOOL_VIP_3D_Z6K1P9Q8": {"type": "3D", "description": "Key VIP 3 ngày"},
  "TBTOOL_VIP_3D_A3Q5F2V7": {"type": "3D", "description": "Key VIP 3 ngày"},
  "TBTOOL_VIP_3D_B8W7D4E1": {"type": "3D", "description": "Key VIP 3 ngày"},
  "TBTOOL_VIP_3D_C1E9L6R3": {"type": "3D", "description": "Key VIP 3 ngày"},
  "TBTOOL_VIP_3D_D6R3M8A9": {"type": "3D", "description": "Key VIP 3 ngày"},
  "TBTOOL_VIP_3D_E2H5N1B4": {"type": "3D", "description": "Key VIP 3 ngày"},
  "TBTOOL_VIP_3D_F9K7X3C6": {"type": "3D", "description": "Key VIP 3 ngày"},
  "TBTOOL_VIP_3D_G4P2V6D8": {"type": "3D", "description": "Key VIP 3 ngày"},
  "TBTOOL_VIP_3D_H5R3T8E2": {"type": "3D", "description": "Key VIP 3 ngày"},
  "TBTOOL_VIP_3D_I2U6W9F7": {"type": "3D", "description": "Key VIP 3 ngày"},
  "TBTOOL_VIP_3D_J7L1M4G3": {"type": "3D", "description": "Key VIP 3 ngày"},
  "TBTOOL_VIP_3D_K9N2P5H8": {"type": "3D", "description": "Key VIP 3 ngày"},
  "TBTOOL_VIP_3D_L8Q6S1I4": {"type": "3D", "description": "Key VIP 3 ngày"},
  "TBTOOL_VIP_3D_M3V7Z9J5": {"type": "3D", "description": "Key VIP 3 ngày"},
  "TBTOOL_VIP_3D_N4X1C6K2": {"type": "3D", "description": "Key VIP 3 ngày"},
  "TBTOOL_VIP_3D_O5Y2D8L9": {"type": "3D", "description": "Key VIP 3 ngày"},
  "TBTOOL_VIP_3D_P6Z3E9M1": {"type": "3D", "description": "Key VIP 3 ngày"},
  "TBTOOL_VIP_3D_Q7A4F1N6": {"type": "3D", "description": "Key VIP 3 ngày"},
  "TBTOOL_VIP_3D_R8B5G2O3": {"type": "3D", "description": "Key VIP 3 ngày"},
  "TBTOOL_VIP_3D_S9C6H3P7": {"type": "3D", "description": "Key VIP 3 ngày"},
  "TBTOOL_VIP_3D_T1D7I4Q8": {"type": "3D", "description": "Key VIP 3 ngày"},
  "TBTOOL_VIP_3D_U2E8J5R4": {"type": "3D", "description": "Key VIP 3 ngày"},
  "TBTOOL_VIP_3D_V3F9K6S1": {"type": "3D", "description": "Key VIP 3 ngày"},
  "TBTOOL_VIP_3D_W4G1L7T9": {"type": "3D", "description": "Key VIP 3 ngày"},
  "TBTOOL_VIP_3D_X5H2M8U6": {"type": "3D", "description": "Key VIP 3 ngày"},
  "TBTOOL_VIP_3D_Y6I3N9V2": {"type": "3D", "description": "Key VIP 3 ngày"},
  "TBTOOL_VIP_3D_Z7J4O1W5": {"type": "3D", "description": "Key VIP 3 ngày"},
  "TBTOOL_VIP_3D_A8K5P2X3": {"type": "3D", "description": "Key VIP 3 ngày"},
  "TBTOOL_VIP_3D_B9L6Q3Y7": {"type": "3D", "description": "Key VIP 3 ngày"},
  "TBTOOL_VIP_3D_C1M7R4Z8": {"type": "3D", "description": "Key VIP 3 ngày"},
  "TBTOOL_VIP_3D_D2N8S5A4": {"type": "3D", "description": "Key VIP 3 ngày"},
  "TBTOOL_VIP_3D_E3O9T6B1": {"type": "3D", "description": "Key VIP 3 ngày"},
  "TBTOOL_VIP_3D_F4P1U7C9": {"type": "3D", "description": "Key VIP 3 ngày"},
  "TBTOOL_VIP_3D_G5Q2V8D6": {"type": "3D", "description": "Key VIP 3 ngày"},
  "TBTOOL_VIP_3D_H6R3W9E2": {"type": "3D", "description": "Key VIP 3 ngày"},
  "TBTOOL_VIP_3D_I7S4X1F5": {"type": "3D", "description": "Key VIP 3 ngày"},
  "TBTOOL_VIP_3D_J8T5Y2G3": {"type": "3D", "description": "Key VIP 3 ngày"},
  "TBTOOL_VIP_3D_K9U6Z3H7": {"type": "3D", "description": "Key VIP 3 ngày"},
  "TBTOOL_VIP_3D_L1V7A4I8": {"type": "3D", "description": "Key VIP 3 ngày"},
  "TBTOOL_VIP_3D_M2W8B5J4": {"type": "3D", "description": "Key VIP 3 ngày"},
  "TBTOOL_VIP_3D_N3X9C6K1": {"type": "3D", "description": "Key VIP 3 ngày"},
  "TBTOOL_VIP_3D_O4Y1D7L9": {"type": "3D", "description": "Key VIP 3 ngày"},
  "TBTOOL_VIP_3D_P5Z2E8M6": {"type": "3D", "description": "Key VIP 3 ngày"},
  "TBTOOL_VIP_3D_Q6A3F9N2": {"type": "3D", "description": "Key VIP 3 ngày"},
  "TBTOOL_VIP_3D_R7B4G1O5": {"type": "3D", "description": "Key VIP 3 ngày"},
  "TBTOOL_VIP_3D_S8C5H2P3": {"type": "3D", "description": "Key VIP 3 ngày"},
  "TBTOOL_VIP_3D_T9D6I3Q7": {"type": "3D", "description": "Key VIP 3 ngày"},
  "TBTOOL_VIP_3D_U1E7J4R8": {"type": "3D", "description": "Key VIP 3 ngày"},
  "TBTOOL_VIP_3D_V2F8K5S4": {"type": "3D", "description": "Key VIP 3 ngày"},
  "TBTOOL_VIP_3D_W3G9L6T1": {"type": "3D", "description": "Key VIP 3 ngày"},
  "TBTOOL_VIP_3D_X4H1M7U9": {"type": "3D", "description": "Key VIP 3 ngày"},
  "TBTOOL_VIP_3D_Y5I2N8V6": {"type": "3D", "description": "Key VIP 3 ngày"},
  "TBTOOL_VIP_3D_Z6J3O9W2": {"type": "3D", "description": "Key VIP 3 ngày"},
  "TBTOOL_VIP_3D_A7K4P1X5": {"type": "3D", "description": "Key VIP 3 ngày"},
  "TBTOOL_VIP_3D_B8L5Q2Y3": {"type": "3D", "description": "Key VIP 3 ngày"},
  "TBTOOL_VIP_3D_C9M6R3Z7": {"type": "3D", "description": "Key VIP 3 ngày"},
  "TBTOOL_VIP_3D_D1N7S4A8": {"type": "3D", "description": "Key VIP 3 ngày"},
  "TBTOOL_VIP_3D_E2O8T5B4": {"type": "3D", "description": "Key VIP 3 ngày"},
  "TBTOOL_VIP_3D_F3P9U6C1": {"type": "3D", "description": "Key VIP 3 ngày"},
  "TBTOOL_VIP_3D_G4Q1V7D9": {"type": "3D", "description": "Key VIP 3 ngày"},
  "TBTOOL_VIP_3D_H5R2W8E6": {"type": "3D", "description": "Key VIP 3 ngày"},
  "TBTOOL_VIP_3D_I6S3X9F2": {"type": "3D", "description": "Key VIP 3 ngày"},
  "TBTOOL_VIP_3D_J7T4Y1G5": {"type": "3D", "description": "Key VIP 3 ngày"},
  "TBTOOL_VIP_3D_K8U5Z2H3": {"type": "3D", "description": "Key VIP 3 ngày"},
  "TBTOOL_VIP_3D_L9V6A3I7": {"type": "3D", "description": "Key VIP 3 ngày"},
  "TBTOOL_VIP_3D_M1W7B4J8": {"type": "3D", "description": "Key VIP 3 ngày"},
  "TBTOOL_VIP_3D_N2X8C5K4": {"type": "3D", "description": "Key VIP 3 ngày"},
  "TBTOOL_VIP_3D_O3Y9D6L1": {"type": "3D", "description": "Key VIP 3 ngày"},
  "TBTOOL_VIP_3D_P4Z1E7M9": {"type": "3D", "description": "Key VIP 3 ngày"},
  "TBTOOL_VIP_3D_Q5A2F8N6": {"type": "3D", "description": "Key VIP 3 ngày"},
  "TBTOOL_VIP_3D_R6B3G9O2": {"type": "3D", "description": "Key VIP 3 ngày"},
  "TBTOOL_VIP_3D_S7C4H1P5": {"type": "3D", "description": "Key VIP 3 ngày"},
  "TBTOOL_VIP_3D_T8D5I2Q3": {"type": "3D", "description": "Key VIP 3 ngày"},
  "TBTOOL_VIP_3D_U9E6J3R7": {"type": "3D", "description": "Key VIP 3 ngày"},
  "TBTOOL_VIP_3D_V1F7K4S8": {"type": "3D", "description": "Key VIP 3 ngày"},
  "TBTOOL_VIP_3D_W2G8L5T4": {"type": "3D", "description": "Key VIP 3 ngày"},
  "TBTOOL_VIP_3D_X3H9M6U1": {"type": "3D", "description": "Key VIP 3 ngày"},
  "TBTOOL_VIP_3D_Y4I1N7V9": {"type": "3D", "description": "Key VIP 3 ngày"},
  "TBTOOL_VIP_3D_Z5J2O8W6": {"type": "3D", "description": "Key VIP 3 ngày"},
  "TBTOOL_VIP_3D_A6K3P9X2": {"type": "3D", "description": "Key VIP 3 ngày"},
  "TBTOOL_VIP_3D_B7L4Q1Y5": {"type": "3D", "description": "Key VIP 3 ngày"},
  "TBTOOL_VIP_3D_C8M5R2Z3": {"type": "3D", "description": "Key VIP 3 ngày"},
  "TBTOOL_VIP_3D_D9N6S3A7": {"type": "3D", "description": "Key VIP 3 ngày"},
  "TBTOOL_VIP_3D_E1O7T4B8": {"type": "3D", "description": "Key VIP 3 ngày"},
  "TBTOOL_VIP_3D_F2P8U5C4": {"type": "3D", "description": "Key VIP 3 ngày"},
  "TBTOOL_VIP_3D_G3Q9V6D1": {"type": "3D", "description": "Key VIP 3 ngày"},
  "TBTOOL_VIP_3D_H4R1W7E9": {"type": "3D", "description": "Key VIP 3 ngày"},
  "TBTOOL_VIP_3D_I5S2X8F6": {"type": "3D", "description": "Key VIP 3 ngày"},
  "TBTOOL_VIP_3D_J6T3Y9G2": {"type": "3D", "description": "Key VIP 3 ngày"},
  "TBTOOL_VIP_3D_K7U4Z1H5": {"type": "3D", "description": "Key VIP 3 ngày"},
  "TBTOOL_VIP_3D_L8V5A2I3": {"type": "3D", "description": "Key VIP 3 ngày"},
  "TBTOOL_VIP_3D_M9W6B3J7": {"type": "3D", "description": "Key VIP 3 ngày"},
  "TBTOOL_VIP_3D_N1X7C4K8": {"type": "3D", "description": "Key VIP 3 ngày"},
  "TBTOOL_VIP_3D_O2Y8D5L4": {"type": "3D", "description": "Key VIP 3 ngày"},
  "TBTOOL_VIP_3D_P3Z9E6M1": {"type": "3D", "description": "Key VIP 3 ngày"},
  "TBTOOL_VIP_3D_Q4A1F7N9": {"type": "3D", "description": "Key VIP 3 ngày"},
  "TBTOOL_VIP_3D_R5B2G8O6": {"type": "3D", "description": "Key VIP 3 ngày"},
  "TBTOOL_VIP_3D_S6C3H9P2": {"type": "3D", "description": "Key VIP 3 ngày"},
  "TBTOOL_VIP_3D_T7D4I1Q5": {"type": "3D", "description": "Key VIP 3 ngày"},
  "TBTOOL_VIP_3D_U8E5J2R3": {"type": "3D", "description": "Key VIP 3 ngày"},
  "TBTOOL_VIP_3D_V9F6K3S7": {"type": "3D", "description": "Key VIP 3 ngày"},
  "TBTOOL_VIP_3D_W1G7L4T8": {"type": "3D", "description": "Key VIP 3 ngày"},
  "TBTOOL_VIP_3D_X2H8M5U4": {"type": "3D", "description": "Key VIP 3 ngày"},
  "TBTOOL_VIP_3D_Y3I9N6V1": {"type": "3D", "description": "Key VIP 3 ngày"},
  "TBTOOL_VIP_3D_Z4J1O7W9": {"type": "3D", "description": "Key VIP 3 ngày"},
  "TBTOOL_VIP_3D_A5K2P8X6": {"type": "3D", "description": "Key VIP 3 ngày"},
  "TBTOOL_VIP_3D_B6L3Q9Y2": {"type": "3D", "description": "Key VIP 3 ngày"},
  "TBTOOL_VIP_3D_C7M4R1Z5": {"type": "3D", "description": "Key VIP 3 ngày"},
  "TBTOOL_VIP_3D_D8N5S2A3": {"type": "3D", "description": "Key VIP 3 ngày"},

  "TBTOOL_VIP_7D_A1B2C3D4": {"type": "7D", "description": "Key VIP 7 ngày"},
  "TBTOOL_VIP_7D_D4E5F6G7": {"type": "7D", "description": "Key VIP 7 ngày"},
  "TBTOOL_VIP_7D_G7H8I9J1": {"type": "7D", "description": "Key VIP 7 ngày"},
  "TBTOOL_VIP_7D_J1K2L3M4": {"type": "7D", "description": "Key VIP 7 ngày"},
  "TBTOOL_VIP_7D_M4N5O6P7": {"type": "7D", "description": "Key VIP 7 ngày"},
  "TBTOOL_VIP_7D_P7Q8R9S1": {"type": "7D", "description": "Key VIP 7 ngày"},
  "TBTOOL_VIP_7D_S1T2U3V4": {"type": "7D", "description": "Key VIP 7 ngày"},
  "TBTOOL_VIP_7D_V4W5X6Y7": {"type": "7D", "description": "Key VIP 7 ngày"},
  "TBTOOL_VIP_7D_Y7Z8A9B1": {"type": "7D", "description": "Key VIP 7 ngày"},
  "TBTOOL_VIP_7D_B1C2D3E4": {"type": "7D", "description": "Key VIP 7 ngày"},
  "TBTOOL_VIP_7D_E4F5G6H7": {"type": "7D", "description": "Key VIP 7 ngày"},
  "TBTOOL_VIP_7D_H7I8J9K1": {"type": "7D", "description": "Key VIP 7 ngày"},
  "TBTOOL_VIP_7D_K1L2M3N4": {"type": "7D", "description": "Key VIP 7 ngày"},
  "TBTOOL_VIP_7D_N4O5P6Q7": {"type": "7D", "description": "Key VIP 7 ngày"},
  "TBTOOL_VIP_7D_Q7R8S9T1": {"type": "7D", "description": "Key VIP 7 ngày"},
  "TBTOOL_VIP_7D_T1U2V3W4": {"type": "7D", "description": "Key VIP 7 ngày"},
  "TBTOOL_VIP_7D_W4X5Y6Z7": {"type": "7D", "description": "Key VIP 7 ngày"},
  "TBTOOL_VIP_7D_Z7A8B9C1": {"type": "7D", "description": "Key VIP 7 ngày"},
  "TBTOOL_VIP_7D_C1D2E3F4": {"type": "7D", "description": "Key VIP 7 ngày"},
  "TBTOOL_VIP_7D_F4G5H6I7": {"type": "7D", "description": "Key VIP 7 ngày"},
  "TBTOOL_VIP_7D_I7J8K9L1": {"type": "7D", "description": "Key VIP 7 ngày"},
  "TBTOOL_VIP_7D_L1M2N3O4": {"type": "7D", "description": "Key VIP 7 ngày"},
  "TBTOOL_VIP_7D_O4P5Q6R7": {"type": "7D", "description": "Key VIP 7 ngày"},
  "TBTOOL_VIP_7D_R7S8T9U1": {"type": "7D", "description": "Key VIP 7 ngày"},
  "TBTOOL_VIP_7D_U1V2W3X4": {"type": "7D", "description": "Key VIP 7 ngày"},
  "TBTOOL_VIP_7D_X4Y5Z6A7": {"type": "7D", "description": "Key VIP 7 ngày"},
  "TBTOOL_VIP_7D_A7B8C9D1": {"type": "7D", "description": "Key VIP 7 ngày"},
  "TBTOOL_VIP_7D_D1E2F3G4": {"type": "7D", "description": "Key VIP 7 ngày"},
  "TBTOOL_VIP_7D_G4H5I6J7": {"type": "7D", "description": "Key VIP 7 ngày"},
  "TBTOOL_VIP_7D_J7K8L9M1": {"type": "7D", "description": "Key VIP 7 ngày"},
  "TBTOOL_VIP_7D_M1N2O3P4": {"type": "7D", "description": "Key VIP 7 ngày"},
  "TBTOOL_VIP_7D_P4Q5R6S7": {"type": "7D", "description": "Key VIP 7 ngày"},
  "TBTOOL_VIP_7D_S7T8U9V1": {"type": "7D", "description": "Key VIP 7 ngày"},
  "TBTOOL_VIP_7D_V1W2X3Y4": {"type": "7D", "description": "Key VIP 7 ngày"},
  "TBTOOL_VIP_7D_Y4Z5A6B7": {"type": "7D", "description": "Key VIP 7 ngày"},
  "TBTOOL_VIP_7D_B7C8D9E1": {"type": "7D", "description": "Key VIP 7 ngày"},
  "TBTOOL_VIP_7D_E1F2G3H4": {"type": "7D", "description": "Key VIP 7 ngày"},
  "TBTOOL_VIP_7D_H4I5J6K7": {"type": "7D", "description": "Key VIP 7 ngày"},
  "TBTOOL_VIP_7D_K7L8M9N1": {"type": "7D", "description": "Key VIP 7 ngày"},
  "TBTOOL_VIP_7D_N1O2P3Q4": {"type": "7D", "description": "Key VIP 7 ngày"},
  "TBTOOL_VIP_7D_Q4R5S6T7": {"type": "7D", "description": "Key VIP 7 ngày"},
  "TBTOOL_VIP_7D_T7U8V9W1": {"type": "7D", "description": "Key VIP 7 ngày"},
  "TBTOOL_VIP_7D_W1X2Y3Z4": {"type": "7D", "description": "Key VIP 7 ngày"},
  "TBTOOL_VIP_7D_Z4A5B6C7": {"type": "7D", "description": "Key VIP 7 ngày"},
  "TBTOOL_VIP_7D_C7D8E9F1": {"type": "7D", "description": "Key VIP 7 ngày"},
  "TBTOOL_VIP_7D_F1G2H3I4": {"type": "7D", "description": "Key VIP 7 ngày"},
  "TBTOOL_VIP_7D_I4J5K6L7": {"type": "7D", "description": "Key VIP 7 ngày"},
  "TBTOOL_VIP_7D_L7M8N9O1": {"type": "7D", "description": "Key VIP 7 ngày"},
  "TBTOOL_VIP_7D_O1P2Q3R4": {"type": "7D", "description": "Key VIP 7 ngày"},
  "TBTOOL_VIP_7D_R4S5T6U7": {"type": "7D", "description": "Key VIP 7 ngày"},
  "TBTOOL_VIP_7D_U7V8W9X1": {"type": "7D", "description": "Key VIP 7 ngày"},
  "TBTOOL_VIP_7D_X1Y2Z3A4": {"type": "7D", "description": "Key VIP 7 ngày"},
  "TBTOOL_VIP_7D_A4B5C6D7": {"type": "7D", "description": "Key VIP 7 ngày"},
  "TBTOOL_VIP_7D_D7E8F9G1": {"type": "7D", "description": "Key VIP 7 ngày"},
  "TBTOOL_VIP_7D_G1H2I3J4": {"type": "7D", "description": "Key VIP 7 ngày"},
  "TBTOOL_VIP_7D_J4K5L6M7": {"type": "7D", "description": "Key VIP 7 ngày"},
  "TBTOOL_VIP_7D_M7N8O9P1": {"type": "7D", "description": "Key VIP 7 ngày"},
  "TBTOOL_VIP_7D_P1Q2R3S4": {"type": "7D", "description": "Key VIP 7 ngày"},
  "TBTOOL_VIP_7D_S4T5U6V7": {"type": "7D", "description": "Key VIP 7 ngày"},
  "TBTOOL_VIP_7D_V7W8X9Y1": {"type": "7D", "description": "Key VIP 7 ngày"},
  "TBTOOL_VIP_7D_Y1Z2A3B4": {"type": "7D", "description": "Key VIP 7 ngày"},
  "TBTOOL_VIP_7D_B4C5D6E7": {"type": "7D", "description": "Key VIP 7 ngày"},
  "TBTOOL_VIP_7D_E7F8G9H1": {"type": "7D", "description": "Key VIP 7 ngày"},
  "TBTOOL_VIP_7D_H1I2J3K4": {"type": "7D", "description": "Key VIP 7 ngày"},
  "TBTOOL_VIP_7D_K4L5M6N7": {"type": "7D", "description": "Key VIP 7 ngày"},
  "TBTOOL_VIP_7D_N7O8P9Q1": {"type": "7D", "description": "Key VIP 7 ngày"},
  "TBTOOL_VIP_7D_Q1R2S3T4": {"type": "7D", "description": "Key VIP 7 ngày"},
  "TBTOOL_VIP_7D_T4U5V6W7": {"type": "7D", "description": "Key VIP 7 ngày"},
  "TBTOOL_VIP_7D_W7X8Y9Z1": {"type": "7D", "description": "Key VIP 7 ngày"},
  "TBTOOL_VIP_7D_Z1A2B3C4": {"type": "7D", "description": "Key VIP 7 ngày"},
  "TBTOOL_VIP_7D_C4D5E6F7": {"type": "7D", "description": "Key VIP 7 ngày"},
  "TBTOOL_VIP_7D_F7G8H9I1": {"type": "7D", "description": "Key VIP 7 ngày"},
  "TBTOOL_VIP_7D_I1J2K3L4": {"type": "7D", "description": "Key VIP 7 ngày"},
  "TBTOOL_VIP_7D_L4M5N6O7": {"type": "7D", "description": "Key VIP 7 ngày"},
  "TBTOOL_VIP_7D_O7P8Q9R1": {"type": "7D", "description": "Key VIP 7 ngày"},
  "TBTOOL_VIP_7D_R1S2T3U4": {"type": "7D", "description": "Key VIP 7 ngày"},
  "TBTOOL_VIP_7D_U4V5W6X7": {"type": "7D", "description": "Key VIP 7 ngày"},
  "TBTOOL_VIP_7D_X7Y8Z9A1": {"type": "7D", "description": "Key VIP 7 ngày"},
  "TBTOOL_VIP_7D_A1B2C3D4": {"type": "7D", "description": "Key VIP 7 ngày"},
  "TBTOOL_VIP_7D_D4E5F6G7": {"type": "7D", "description": "Key VIP 7 ngày"},
  "TBTOOL_VIP_7D_G7H8I9J1": {"type": "7D", "description": "Key VIP 7 ngày"},
  "TBTOOL_VIP_7D_J1K2L3M4": {"type": "7D", "description": "Key VIP 7 ngày"},
  "TBTOOL_VIP_7D_M4N5O6P7": {"type": "7D", "description": "Key VIP 7 ngày"},
  "TBTOOL_VIP_7D_P7Q8R9S1": {"type": "7D", "description": "Key VIP 7 ngày"},
  "TBTOOL_VIP_7D_S1T2U3V4": {"type": "7D", "description": "Key VIP 7 ngày"},
  "TBTOOL_VIP_7D_V4W5X6Y7": {"type": "7D", "description": "Key VIP 7 ngày"},
  "TBTOOL_VIP_7D_Y7Z8A9B1": {"type": "7D", "description": "Key VIP 7 ngày"},
  "TBTOOL_VIP_7D_B1C2D3E4": {"type": "7D", "description": "Key VIP 7 ngày"},
  "TBTOOL_VIP_7D_E4F5G6H7": {"type": "7D", "description": "Key VIP 7 ngày"},
  "TBTOOL_VIP_7D_H7I8J9K1": {"type": "7D", "description": "Key VIP 7 ngày"},
  "TBTOOL_VIP_7D_K1L2M3N4": {"type": "7D", "description": "Key VIP 7 ngày"},
  "TBTOOL_VIP_7D_N4O5P6Q7": {"type": "7D", "description": "Key VIP 7 ngày"},
  "TBTOOL_VIP_7D_Q7R8S9T1": {"type": "7D", "description": "Key VIP 7 ngày"},
  "TBTOOL_VIP_7D_T1U2V3W4": {"type": "7D", "description": "Key VIP 7 ngày"},
  "TBTOOL_VIP_7D_W4X5Y6Z7": {"type": "7D", "description": "Key VIP 7 ngày"},
  "TBTOOL_VIP_7D_Z7A8B9C1": {"type": "7D", "description": "Key VIP 7 ngày"},
  "TBTOOL_VIP_7D_C1D2E3F4": {"type": "7D", "description": "Key VIP 7 ngày"},
  "TBTOOL_VIP_7D_F4G5H6I7": {"type": "7D", "description": "Key VIP 7 ngày"},
  "TBTOOL_VIP_7D_I7J8K9L1": {"type": "7D", "description": "Key VIP 7 ngày"},
  "TBTOOL_VIP_7D_L1M2N3O4": {"type": "7D", "description": "Key VIP 7 ngày"},
  "TBTOOL_VIP_7D_O4P5Q6R7": {"type": "7D", "description": "Key VIP 7 ngày"},
  "TBTOOL_VIP_7D_R7S8T9U1": {"type": "7D", "description": "Key VIP 7 ngày"},
  "TBTOOL_VIP_7D_U1V2W3X4": {"type": "7D", "description": "Key VIP 7 ngày"},
  "TBTOOL_VIP_7D_X4Y5Z6A7": {"type": "7D", "description": "Key VIP 7 ngày"},
  "TBTOOL_VIP_7D_A7B8C9D1": {"type": "7D", "description": "Key VIP 7 ngày"},
  "TBTOOL_VIP_7D_D1E2F3G4": {"type": "7D", "description": "Key VIP 7 ngày"},
  "TBTOOL_VIP_7D_G4H5I6J7": {"type": "7D", "description": "Key VIP 7 ngày"},
  "TBTOOL_VIP_7D_J7K8L9M1": {"type": "7D", "description": "Key VIP 7 ngày"},
  "TBTOOL_VIP_7D_M1N2O3P4": {"type": "7D", "description": "Key VIP 7 ngày"},
  "TBTOOL_VIP_7D_P4Q5R6S7": {"type": "7D", "description": "Key VIP 7 ngày"},
  "TBTOOL_VIP_7D_S7T8U9V1": {"type": "7D", "description": "Key VIP 7 ngày"},
  "TBTOOL_VIP_7D_V1W2X3Y4": {"type": "7D", "description": "Key VIP 7 ngày"},
  "TBTOOL_VIP_7D_Y4Z5A6B7": {"type": "7D", "description": "Key VIP 7 ngày"},
  "TBTOOL_VIP_7D_B7C8D9E1": {"type": "7D", "description": "Key VIP 7 ngày"},

  "TBTOOL_VIP_15D_Q4R5S6T7": {"type": "15D", "description": "Key VIP 15 ngày"},
  "TBTOOL_VIP_15D_T7U8V9W1": {"type": "15D", "description": "Key VIP 15 ngày"},
  "TBTOOL_VIP_15D_W1X2Y3Z4": {"type": "15D", "description": "Key VIP 15 ngày"},
  "TBTOOL_VIP_15D_Z4A5B6C7": {"type": "15D", "description": "Key VIP 15 ngày"},
  "TBTOOL_VIP_15D_C7D8E9F1": {"type": "15D", "description": "Key VIP 15 ngày"},
  "TBTOOL_VIP_15D_F1G2H3I4": {"type": "15D", "description": "Key VIP 15 ngày"},
  "TBTOOL_VIP_15D_I4J5K6L7": {"type": "15D", "description": "Key VIP 15 ngày"},
  "TBTOOL_VIP_15D_L7M8N9O1": {"type": "15D", "description": "Key VIP 15 ngày"},
  "TBTOOL_VIP_15D_O1P2Q3R4": {"type": "15D", "description": "Key VIP 15 ngày"},
  "TBTOOL_VIP_15D_R4S5T6U7": {"type": "15D", "description": "Key VIP 15 ngày"},
  "TBTOOL_VIP_15D_U7V8W9X1": {"type": "15D", "description": "Key VIP 15 ngày"},
  "TBTOOL_VIP_15D_X1Y2Z3A4": {"type": "15D", "description": "Key VIP 15 ngày"},
  "TBTOOL_VIP_15D_A4B5C6D7": {"type": "15D", "description": "Key VIP 15 ngày"},
  "TBTOOL_VIP_15D_D7E8F9G1": {"type": "15D", "description": "Key VIP 15 ngày"},
  "TBTOOL_VIP_15D_G1H2I3J4": {"type": "15D", "description": "Key VIP 15 ngày"},
  "TBTOOL_VIP_15D_J4K5L6M7": {"type": "15D", "description": "Key VIP 15 ngày"},
  "TBTOOL_VIP_15D_M7N8O9P1": {"type": "15D", "description": "Key VIP 15 ngày"},
  "TBTOOL_VIP_15D_P1Q2R3S4": {"type": "15D", "description": "Key VIP 15 ngày"},
  "TBTOOL_VIP_15D_S4T5U6V7": {"type": "15D", "description": "Key VIP 15 ngày"},
  "TBTOOL_VIP_15D_V7W8X9Y1": {"type": "15D", "description": "Key VIP 15 ngày"},
  "TBTOOL_VIP_15D_Y1Z2A3B4": {"type": "15D", "description": "Key VIP 15 ngày"},
  "TBTOOL_VIP_15D_B4C5D6E7": {"type": "15D", "description": "Key VIP 15 ngày"},
  "TBTOOL_VIP_15D_E7F8G9H1": {"type": "15D", "description": "Key VIP 15 ngày"},
  "TBTOOL_VIP_15D_H1I2J3K4": {"type": "15D", "description": "Key VIP 15 ngày"},
  "TBTOOL_VIP_15D_K4L5M6N7": {"type": "15D", "description": "Key VIP 15 ngày"},
  "TBTOOL_VIP_15D_N7O8P9Q1": {"type": "15D", "description": "Key VIP 15 ngày"},
  "TBTOOL_VIP_15D_Q1R2S3T4": {"type": "15D", "description": "Key VIP 15 ngày"},
  "TBTOOL_VIP_15D_T4U5V6W7": {"type": "15D", "description": "Key VIP 15 ngày"},
  "TBTOOL_VIP_15D_W7X8Y9Z1": {"type": "15D", "description": "Key VIP 15 ngày"},
  "TBTOOL_VIP_15D_Z1A2B3C4": {"type": "15D", "description": "Key VIP 15 ngày"},
  "TBTOOL_VIP_15D_C4D5E6F7": {"type": "15D", "description": "Key VIP 15 ngày"},
  "TBTOOL_VIP_15D_F7G8H9I1": {"type": "15D", "description": "Key VIP 15 ngày"},
  "TBTOOL_VIP_15D_I1J2K3L4": {"type": "15D", "description": "Key VIP 15 ngày"},
  "TBTOOL_VIP_15D_L4M5N6O7": {"type": "15D", "description": "Key VIP 15 ngày"},
  "TBTOOL_VIP_15D_O7P8Q9R1": {"type": "15D", "description": "Key VIP 15 ngày"},
  "TBTOOL_VIP_15D_R1S2T3U4": {"type": "15D", "description": "Key VIP 15 ngày"},
  "TBTOOL_VIP_15D_U4V5W6X7": {"type": "15D", "description": "Key VIP 15 ngày"},
  "TBTOOL_VIP_15D_X7Y8Z9A1": {"type": "15D", "description": "Key VIP 15 ngày"},
  "TBTOOL_VIP_15D_A1B2C3D4": {"type": "15D", "description": "Key VIP 15 ngày"},
  "TBTOOL_VIP_15D_D4E5F6G7": {"type": "15D", "description": "Key VIP 15 ngày"},
  "TBTOOL_VIP_15D_G7H8I9J1": {"type": "15D", "description": "Key VIP 15 ngày"},
  "TBTOOL_VIP_15D_J1K2L3M4": {"type": "15D", "description": "Key VIP 15 ngày"},
  "TBTOOL_VIP_15D_M4N5O6P7": {"type": "15D", "description": "Key VIP 15 ngày"},
  "TBTOOL_VIP_15D_P7Q8R9S1": {"type": "15D", "description": "Key VIP 15 ngày"},
  "TBTOOL_VIP_15D_S1T2U3V4": {"type": "15D", "description": "Key VIP 15 ngày"},
  "TBTOOL_VIP_15D_V4W5X6Y7": {"type": "15D", "description": "Key VIP 15 ngày"},
  "TBTOOL_VIP_15D_Y7Z8A9B1": {"type": "15D", "description": "Key VIP 15 ngày"},
  "TBTOOL_VIP_15D_B1C2D3E4": {"type": "15D", "description": "Key VIP 15 ngày"},
  "TBTOOL_VIP_15D_E4F5G6H7": {"type": "15D", "description": "Key VIP 15 ngày"},
  "TBTOOL_VIP_15D_H7I8J9K1": {"type": "15D", "description": "Key VIP 15 ngày"},
  "TBTOOL_VIP_15D_K1L2M3N4": {"type": "15D", "description": "Key VIP 15 ngày"},
  "TBTOOL_VIP_15D_N4O5P6Q7": {"type": "15D", "description": "Key VIP 15 ngày"},
  "TBTOOL_VIP_15D_Q7R8S9T1": {"type": "15D", "description": "Key VIP 15 ngày"},
  "TBTOOL_VIP_15D_T1U2V3W4": {"type": "15D", "description": "Key VIP 15 ngày"},
  "TBTOOL_VIP_15D_W4X5Y6Z7": {"type": "15D", "description": "Key VIP 15 ngày"},
  "TBTOOL_VIP_15D_Z7A8B9C1": {"type": "15D", "description": "Key VIP 15 ngày"},
  "TBTOOL_VIP_15D_C1D2E3F4": {"type": "15D", "description": "Key VIP 15 ngày"},
  "TBTOOL_VIP_15D_F4G5H6I7": {"type": "15D", "description": "Key VIP 15 ngày"},
  "TBTOOL_VIP_15D_I7J8K9L1": {"type": "15D", "description": "Key VIP 15 ngày"},
  "TBTOOL_VIP_15D_L1M2N3O4": {"type": "15D", "description": "Key VIP 15 ngày"},
  "TBTOOL_VIP_15D_O4P5Q6R7": {"type": "15D", "description": "Key VIP 15 ngày"},
  "TBTOOL_VIP_15D_R7S8T9U1": {"type": "15D", "description": "Key VIP 15 ngày"},
  "TBTOOL_VIP_15D_U1V2W3X4": {"type": "15D", "description": "Key VIP 15 ngày"},
  "TBTOOL_VIP_15D_X4Y5Z6A7": {"type": "15D", "description": "Key VIP 15 ngày"},
  "TBTOOL_VIP_15D_A7B8C9D1": {"type": "15D", "description": "Key VIP 15 ngày"},
  "TBTOOL_VIP_15D_D1E2F3G4": {"type": "15D", "description": "Key VIP 15 ngày"},
  "TBTOOL_VIP_15D_G4H5I6J7": {"type": "15D", "description": "Key VIP 15 ngày"},
  "TBTOOL_VIP_15D_J7K8L9M1": {"type": "15D", "description": "Key VIP 15 ngày"},
  "TBTOOL_VIP_15D_M1N2O3P4": {"type": "15D", "description": "Key VIP 15 ngày"},
  "TBTOOL_VIP_15D_P4Q5R6S7": {"type": "15D", "description": "Key VIP 15 ngày"},
  "TBTOOL_VIP_15D_S7T8U9V1": {"type": "15D", "description": "Key VIP 15 ngày"},
  "TBTOOL_VIP_15D_V1W2X3Y4": {"type": "15D", "description": "Key VIP 15 ngày"},
  "TBTOOL_VIP_15D_Y4Z5A6B7": {"type": "15D", "description": "Key VIP 15 ngày"},
  "TBTOOL_VIP_15D_B7C8D9E1": {"type": "15D", "description": "Key VIP 15 ngày"},
  "TBTOOL_VIP_15D_E1F2G3H4": {"type": "15D", "description": "Key VIP 15 ngày"},
  "TBTOOL_VIP_15D_H4I5J6K7": {"type": "15D", "description": "Key VIP 15 ngày"},
  "TBTOOL_VIP_15D_K7L8M9N1": {"type": "15D", "description": "Key VIP 15 ngày"},
  "TBTOOL_VIP_15D_N1O2P3Q4": {"type": "15D", "description": "Key VIP 15 ngày"},
  "TBTOOL_VIP_15D_Q4R5S6T7": {"type": "15D", "description": "Key VIP 15 ngày"},
  "TBTOOL_VIP_15D_T7U8V9W1": {"type": "15D", "description": "Key VIP 15 ngày"},
  "TBTOOL_VIP_15D_W1X2Y3Z4": {"type": "15D", "description": "Key VIP 15 ngày"},
  "TBTOOL_VIP_15D_Z4A5B6C7": {"type": "15D", "description": "Key VIP 15 ngày"},
  "TBTOOL_VIP_15D_C7D8E9F1": {"type": "15D", "description": "Key VIP 15 ngày"},
  "TBTOOL_VIP_15D_F1G2H3I4": {"type": "15D", "description": "Key VIP 15 ngày"},
  "TBTOOL_VIP_15D_I4J5K6L7": {"type": "15D", "description": "Key VIP 15 ngày"},
  "TBTOOL_VIP_15D_L7M8N9O1": {"type": "15D", "description": "Key VIP 15 ngày"},
  "TBTOOL_VIP_15D_O1P2Q3R4": {"type": "15D", "description": "Key VIP 15 ngày"},
  "TBTOOL_VIP_15D_R4S5T6U7": {"type": "15D", "description": "Key VIP 15 ngày"},
  "TBTOOL_VIP_15D_U7V8W9X1": {"type": "15D", "description": "Key VIP 15 ngày"},
  "TBTOOL_VIP_15D_X1Y2Z3A4": {"type": "15D", "description": "Key VIP 15 ngày"},
  "TBTOOL_VIP_15D_A4B5C6D7": {"type": "15D", "description": "Key VIP 15 ngày"},
  "TBTOOL_VIP_15D_D7E8F9G1": {"type": "15D", "description": "Key VIP 15 ngày"},
  "TBTOOL_VIP_15D_G1H2I3J4": {"type": "15D", "description": "Key VIP 15 ngày"},
  "TBTOOL_VIP_15D_J4K5L6M7": {"type": "15D", "description": "Key VIP 15 ngày"},
  "TBTOOL_VIP_15D_M7N8O9P1": {"type": "15D", "description": "Key VIP 15 ngày"},
  "TBTOOL_VIP_15D_P1Q2R3S4": {"type": "15D", "description": "Key VIP 15 ngày"},
  "TBTOOL_VIP_15D_S4T5U6V7": {"type": "15D", "description": "Key VIP 15 ngày"},
  "TBTOOL_VIP_15D_V7W8X9Y1": {"type": "15D", "description": "Key VIP 15 ngày"},
  "TBTOOL_VIP_15D_Y1Z2A3B4": {"type": "15D", "description": "Key VIP 15 ngày"},
  "TBTOOL_VIP_15D_B4C5D6E7": {"type": "15D", "description": "Key VIP 15 ngày"},
  "TBTOOL_VIP_15D_E7F8G9H1": {"type": "15D", "description": "Key VIP 15 ngày"},
  "TBTOOL_VIP_15D_H1I2J3K4": {"type": "15D", "description": "Key VIP 15 ngày"},
  "TBTOOL_VIP_15D_K4L5M6N7": {"type": "15D", "description": "Key VIP 15 ngày"},
  "TBTOOL_VIP_15D_N7O8P9Q1": {"type": "15D", "description": "Key VIP 15 ngày"},
  "TBTOOL_VIP_15D_Q1R2S3T4": {"type": "15D", "description": "Key VIP 15 ngày"},
  "TBTOOL_VIP_15D_T4U5V6W7": {"type": "15D", "description": "Key VIP 15 ngày"},
  "TBTOOL_VIP_15D_W7X8Y9Z1": {"type": "15D", "description": "Key VIP 15 ngày"},
  "TBTOOL_VIP_15D_Z1A2B3C4": {"type": "15D", "description": "Key VIP 15 ngày"},
  "TBTOOL_VIP_15D_C4D5E6F7": {"type": "15D", "description": "Key VIP 15 ngày"},

  "TBTOOL_VIP_30D_N7O8P9Q1": {"type": "30D", "description": "Key VIP 30 ngày"},
  "TBTOOL_VIP_30D_Q1R2S3T4": {"type": "30D", "description": "Key VIP 30 ngày"},
  "TBTOOL_VIP_30D_T4U5V6W7": {"type": "30D", "description": "Key VIP 30 ngày"},
  "TBTOOL_VIP_30D_W7X8Y9Z1": {"type": "30D", "description": "Key VIP 30 ngày"},
  "TBTOOL_VIP_30D_Z1A2B3C4": {"type": "30D", "description": "Key VIP 30 ngày"},
  "TBTOOL_VIP_30D_C4D5E6F7": {"type": "30D", "description": "Key VIP 30 ngày"},
  "TBTOOL_VIP_30D_F7G8H9I1": {"type": "30D", "description": "Key VIP 30 ngày"},
  "TBTOOL_VIP_30D_I1J2K3L4": {"type": "30D", "description": "Key VIP 30 ngày"},
  "TBTOOL_VIP_30D_L4M5N6O7": {"type": "30D", "description": "Key VIP 30 ngày"},
  "TBTOOL_VIP_30D_O7P8Q9R1": {"type": "30D", "description": "Key VIP 30 ngày"},
  "TBTOOL_VIP_30D_R1S2T3U4": {"type": "30D", "description": "Key VIP 30 ngày"},
  "TBTOOL_VIP_30D_U4V5W6X7": {"type": "30D", "description": "Key VIP 30 ngày"},
  "TBTOOL_VIP_30D_X7Y8Z9A1": {"type": "30D", "description": "Key VIP 30 ngày"},
  "TBTOOL_VIP_30D_A1B2C3D4": {"type": "30D", "description": "Key VIP 30 ngày"},
  "TBTOOL_VIP_30D_D4E5F6G7": {"type": "30D", "description": "Key VIP 30 ngày"},
  "TBTOOL_VIP_30D_G7H8I9J1": {"type": "30D", "description": "Key VIP 30 ngày"},
  "TBTOOL_VIP_30D_J1K2L3M4": {"type": "30D", "description": "Key VIP 30 ngày"},
  "TBTOOL_VIP_30D_M4N5O6P7": {"type": "30D", "description": "Key VIP 30 ngày"},
  "TBTOOL_VIP_30D_P7Q8R9S1": {"type": "30D", "description": "Key VIP 30 ngày"},
  "TBTOOL_VIP_30D_S1T2U3V4": {"type": "30D", "description": "Key VIP 30 ngày"},
  "TBTOOL_VIP_30D_V4W5X6Y7": {"type": "30D", "description": "Key VIP 30 ngày"},
  "TBTOOL_VIP_30D_Y7Z8A9B1": {"type": "30D", "description": "Key VIP 30 ngày"},
  "TBTOOL_VIP_30D_B1C2D3E4": {"type": "30D", "description": "Key VIP 30 ngày"},
  "TBTOOL_VIP_30D_E4F5G6H7": {"type": "30D", "description": "Key VIP 30 ngày"},
  "TBTOOL_VIP_30D_H7I8J9K1": {"type": "30D", "description": "Key VIP 30 ngày"},
  "TBTOOL_VIP_30D_K1L2M3N4": {"type": "30D", "description": "Key VIP 30 ngày"},
  "TBTOOL_VIP_30D_N4O5P6Q7": {"type": "30D", "description": "Key VIP 30 ngày"},
  "TBTOOL_VIP_30D_Q7R8S9T1": {"type": "30D", "description": "Key VIP 30 ngày"},
  "TBTOOL_VIP_30D_T1U2V3W4": {"type": "30D", "description": "Key VIP 30 ngày"},
  "TBTOOL_VIP_30D_W4X5Y6Z7": {"type": "30D", "description": "Key VIP 30 ngày"},
  "TBTOOL_VIP_30D_Z7A8B9C1": {"type": "30D", "description": "Key VIP 30 ngày"},
  "TBTOOL_VIP_30D_C1D2E3F4": {"type": "30D", "description": "Key VIP 30 ngày"},
  "TBTOOL_VIP_30D_F4G5H6I7": {"type": "30D", "description": "Key VIP 30 ngày"},
  "TBTOOL_VIP_30D_I7J8K9L1": {"type": "30D", "description": "Key VIP 30 ngày"},
  "TBTOOL_VIP_30D_L1M2N3O4": {"type": "30D", "description": "Key VIP 30 ngày"},
  "TBTOOL_VIP_30D_O4P5Q6R7": {"type": "30D", "description": "Key VIP 30 ngày"},
  "TBTOOL_VIP_30D_R7S8T9U1": {"type": "30D", "description": "Key VIP 30 ngày"},
  "TBTOOL_VIP_30D_U1V2W3X4": {"type": "30D", "description": "Key VIP 30 ngày"},
  "TBTOOL_VIP_30D_X4Y5Z6A7": {"type": "30D", "description": "Key VIP 30 ngày"},
  "TBTOOL_VIP_30D_A7B8C9D1": {"type": "30D", "description": "Key VIP 30 ngày"},
  "TBTOOL_VIP_30D_D1E2F3G4": {"type": "30D", "description": "Key VIP 30 ngày"},
  "TBTOOL_VIP_30D_G4H5I6J7": {"type": "30D", "description": "Key VIP 30 ngày"},
  "TBTOOL_VIP_30D_J7K8L9M1": {"type": "30D", "description": "Key VIP 30 ngày"},
  "TBTOOL_VIP_30D_M1N2O3P4": {"type": "30D", "description": "Key VIP 30 ngày"},
  "TBTOOL_VIP_30D_P4Q5R6S7": {"type": "30D", "description": "Key VIP 30 ngày"},
  "TBTOOL_VIP_30D_S7T8U9V1": {"type": "30D", "description": "Key VIP 30 ngày"},
  "TBTOOL_VIP_30D_V1W2X3Y4": {"type": "30D", "description": "Key VIP 30 ngày"},
  "TBTOOL_VIP_30D_Y4Z5A6B7": {"type": "30D", "description": "Key VIP 30 ngày"},
  "TBTOOL_VIP_30D_B7C8D9E1": {"type": "30D", "description": "Key VIP 30 ngày"},
  "TBTOOL_VIP_30D_E1F2G3H4": {"type": "30D", "description": "Key VIP 30 ngày"},
  "TBTOOL_VIP_30D_H4I5J6K7": {"type": "30D", "description": "Key VIP 30 ngày"},
  "TBTOOL_VIP_30D_K7L8M9N1": {"type": "30D", "description": "Key VIP 30 ngày"},
  "TBTOOL_VIP_30D_N1O2P3Q4": {"type": "30D", "description": "Key VIP 30 ngày"},
  "TBTOOL_VIP_30D_Q4R5S6T7": {"type": "30D", "description": "Key VIP 30 ngày"},
  "TBTOOL_VIP_30D_T7U8V9W1": {"type": "30D", "description": "Key VIP 30 ngày"},
  "TBTOOL_VIP_30D_W1X2Y3Z4": {"type": "30D", "description": "Key VIP 30 ngày"},
  "TBTOOL_VIP_30D_Z4A5B6C7": {"type": "30D", "description": "Key VIP 30 ngày"},
  "TBTOOL_VIP_30D_C7D8E9F1": {"type": "30D", "description": "Key VIP 30 ngày"},
  "TBTOOL_VIP_30D_F1G2H3I4": {"type": "30D", "description": "Key VIP 30 ngày"},
  "TBTOOL_VIP_30D_I4J5K6L7": {"type": "30D", "description": "Key VIP 30 ngày"},
  "TBTOOL_VIP_30D_L7M8N9O1": {"type": "30D", "description": "Key VIP 30 ngày"},
  "TBTOOL_VIP_30D_O1P2Q3R4": {"type": "30D", "description": "Key VIP 30 ngày"},
  "TBTOOL_VIP_30D_R4S5T6U7": {"type": "30D", "description": "Key VIP 30 ngày"},
  "TBTOOL_VIP_30D_U7V8W9X1": {"type": "30D", "description": "Key VIP 30 ngày"},
  "TBTOOL_VIP_30D_X1Y2Z3A4": {"type": "30D", "description": "Key VIP 30 ngày"},
  "TBTOOL_VIP_30D_A4B5C6D7": {"type": "30D", "description": "Key VIP 30 ngày"},
  "TBTOOL_VIP_30D_D7E8F9G1": {"type": "30D", "description": "Key VIP 30 ngày"},
  "TBTOOL_VIP_30D_G1H2I3J4": {"type": "30D", "description": "Key VIP 30 ngày"},
  "TBTOOL_VIP_30D_J4K5L6M7": {"type": "30D", "description": "Key VIP 30 ngày"},
  "TBTOOL_VIP_30D_M7N8O9P1": {"type": "30D", "description": "Key VIP 30 ngày"},
  "TBTOOL_VIP_30D_P1Q2R3S4": {"type": "30D", "description": "Key VIP 30 ngày"},
  "TBTOOL_VIP_30D_S4T5U6V7": {"type": "30D", "description": "Key VIP 30 ngày"},
  "TBTOOL_VIP_30D_V7W8X9Y1": {"type": "30D", "description": "Key VIP 30 ngày"},
  "TBTOOL_VIP_30D_Y1Z2A3B4": {"type": "30D", "description": "Key VIP 30 ngày"},
  "TBTOOL_VIP_30D_B4C5D6E7": {"type": "30D", "description": "Key VIP 30 ngày"},
  "TBTOOL_VIP_30D_E7F8G9H1": {"type": "30D", "description": "Key VIP 30 ngày"},
  "TBTOOL_VIP_30D_H1I2J3K4": {"type": "30D", "description": "Key VIP 30 ngày"},
  "TBTOOL_VIP_30D_K4L5M6N7": {"type": "30D", "description": "Key VIP 30 ngày"},
  "TBTOOL_VIP_30D_N7O8P9Q1": {"type": "30D", "description": "Key VIP 30 ngày"},
  "TBTOOL_VIP_30D_Q1R2S3T4": {"type": "30D", "description": "Key VIP 30 ngày"},
  "TBTOOL_VIP_30D_T4U5V6W7": {"type": "30D", "description": "Key VIP 30 ngày"},
  "TBTOOL_VIP_30D_W7X8Y9Z1": {"type": "30D", "description": "Key VIP 30 ngày"},
  "TBTOOL_VIP_30D_Z1A2B3C4": {"type": "30D", "description": "Key VIP 30 ngày"},
  "TBTOOL_VIP_30D_C4D5E6F7": {"type": "30D", "description": "Key VIP 30 ngày"},
  "TBTOOL_VIP_30D_F7G8H9I1": {"type": "30D", "description": "Key VIP 30 ngày"},
  "TBTOOL_VIP_30D_I1J2K3L4": {"type": "30D", "description": "Key VIP 30 ngày"},
  "TBTOOL_VIP_30D_L4M5N6O7": {"type": "30D", "description": "Key VIP 30 ngày"},
  "TBTOOL_VIP_30D_O7P8Q9R1": {"type": "30D", "description": "Key VIP 30 ngày"},
  "TBTOOL_VIP_30D_R1S2T3U4": {"type": "30D", "description": "Key VIP 30 ngày"},
  "TBTOOL_VIP_30D_U4V5W6X7": {"type": "30D", "description": "Key VIP 30 ngày"},
  "TBTOOL_VIP_30D_X7Y8Z9A1": {"type": "30D", "description": "Key VIP 30 ngày"},
  "TBTOOL_VIP_30D_A1B2C3D4": {"type": "30D", "description": "Key VIP 30 ngày"},
  "TBTOOL_VIP_30D_D4E5F6G7": {"type": "30D", "description": "Key VIP 30 ngày"},
  "TBTOOL_VIP_30D_G7H8I9J1": {"type": "30D", "description": "Key VIP 30 ngày"},
  "TBTOOL_VIP_30D_J1K2L3M4": {"type": "30D", "description": "Key VIP 30 ngày"},
  "TBTOOL_VIP_30D_M4N5O6P7": {"type": "30D", "description": "Key VIP 30 ngày"},
  "TBTOOL_VIP_30D_P7Q8R9S1": {"type": "30D", "description": "Key VIP 30 ngày"},
  "TBTOOL_VIP_30D_S1T2U3V4": {"type": "30D", "description": "Key VIP 30 ngày"},
  "TBTOOL_VIP_30D_V4W5X6Y7": {"type": "30D", "description": "Key VIP 30 ngày"},
  "TBTOOL_VIP_30D_Y7Z8A9B1": {"type": "30D", "description": "Key VIP 30 ngày"},
  "TBTOOL_VIP_30D_B1C2D3E4": {"type": "30D", "description": "Key VIP 30 ngày"},
  "TBTOOL_VIP_30D_E4F5G6H7": {"type": "30D", "description": "Key VIP 30 ngày"},
  "TBTOOL_VIP_30D_H7I8J9K1": {"type": "30D", "description": "Key VIP 30 ngày"},
  "TBTOOL_VIP_30D_K1L2M3N4": {"type": "30D", "description": "Key VIP 30 ngày"},
  "TBTOOL_VIP_30D_N4O5P6Q7": {"type": "30D", "description": "Key VIP 30 ngày"},
  "TBTOOL_VIP_30D_Q7R8S9T1": {"type": "30D", "description": "Key VIP 30 ngày"},
  "TBTOOL_VIP_30D_T1U2V3W4": {"type": "30D", "description": "Key VIP 30 ngày"},
  "TBTOOL_VIP_30D_W4X5Y6Z7": {"type": "30D", "description": "Key VIP 30 ngày"},
  "TBTOOL_VIP_30D_Z7A8B9C1": {"type": "30D", "description": "Key VIP 30 ngày"},

  "TBTOOL_VIP_6M_Z7A8B9C1": {"type": "6M", "description": "Key VIP 6 tháng"},
  "TBTOOL_VIP_6M_C1D2E3F4": {"type": "6M", "description": "Key VIP 6 tháng"},
  "TBTOOL_VIP_6M_F4G5H6I7": {"type": "6M", "description": "Key VIP 6 tháng"},
  "TBTOOL_VIP_6M_I7J8K9L1": {"type": "6M", "description": "Key VIP 6 tháng"},
  "TBTOOL_VIP_6M_L1M2N3O4": {"type": "6M", "description": "Key VIP 6 tháng"},
  "TBTOOL_VIP_6M_O4P5Q6R7": {"type": "6M", "description": "Key VIP 6 tháng"},
  "TBTOOL_VIP_6M_R7S8T9U1": {"type": "6M", "description": "Key VIP 6 tháng"},
  "TBTOOL_VIP_6M_U1V2W3X4": {"type": "6M", "description": "Key VIP 6 tháng"},
  "TBTOOL_VIP_6M_X4Y5Z6A7": {"type": "6M", "description": "Key VIP 6 tháng"},
  "TBTOOL_VIP_6M_A7B8C9D1": {"type": "6M", "description": "Key VIP 6 tháng"},
  "TBTOOL_VIP_6M_D1E2F3G4": {"type": "6M", "description": "Key VIP 6 tháng"},
  "TBTOOL_VIP_6M_G4H5I6J7": {"type": "6M", "description": "Key VIP 6 tháng"},
  "TBTOOL_VIP_6M_J7K8L9M1": {"type": "6M", "description": "Key VIP 6 tháng"},
  "TBTOOL_VIP_6M_M1N2O3P4": {"type": "6M", "description": "Key VIP 6 tháng"},
  "TBTOOL_VIP_6M_P4Q5R6S7": {"type": "6M", "description": "Key VIP 6 tháng"},
  "TBTOOL_VIP_6M_S7T8U9V1": {"type": "6M", "description": "Key VIP 6 tháng"},
  "TBTOOL_VIP_6M_V1W2X3Y4": {"type": "6M", "description": "Key VIP 6 tháng"},
  "TBTOOL_VIP_6M_Y4Z5A6B7": {"type": "6M", "description": "Key VIP 6 tháng"},
  "TBTOOL_VIP_6M_B7C8D9E1": {"type": "6M", "description": "Key VIP 6 tháng"},
  "TBTOOL_VIP_6M_E1F2G3H4": {"type": "6M", "description": "Key VIP 6 tháng"},
  "TBTOOL_VIP_6M_H4I5J6K7": {"type": "6M", "description": "Key VIP 6 tháng"},
  "TBTOOL_VIP_6M_K7L8M9N1": {"type": "6M", "description": "Key VIP 6 tháng"},
  "TBTOOL_VIP_6M_N1O2P3Q4": {"type": "6M", "description": "Key VIP 6 tháng"},
  "TBTOOL_VIP_6M_Q4R5S6T7": {"type": "6M", "description": "Key VIP 6 tháng"},
  "TBTOOL_VIP_6M_T7U8V9W1": {"type": "6M", "description": "Key VIP 6 tháng"},
  "TBTOOL_VIP_6M_W1X2Y3Z4": {"type": "6M", "description": "Key VIP 6 tháng"},
  "TBTOOL_VIP_6M_Z4A5B6C7": {"type": "6M", "description": "Key VIP 6 tháng"},
  "TBTOOL_VIP_6M_C7D8E9F1": {"type": "6M", "description": "Key VIP 6 tháng"},
  "TBTOOL_VIP_6M_F1G2H3I4": {"type": "6M", "description": "Key VIP 6 tháng"},
  "TBTOOL_VIP_6M_I4J5K6L7": {"type": "6M", "description": "Key VIP 6 tháng"},
  "TBTOOL_VIP_6M_L7M8N9O1": {"type": "6M", "description": "Key VIP 6 tháng"},
  "TBTOOL_VIP_6M_O1P2Q3R4": {"type": "6M", "description": "Key VIP 6 tháng"},
  "TBTOOL_VIP_6M_R4S5T6U7": {"type": "6M", "description": "Key VIP 6 tháng"},
  "TBTOOL_VIP_6M_U7V8W9X1": {"type": "6M", "description": "Key VIP 6 tháng"},
  "TBTOOL_VIP_6M_X1Y2Z3A4": {"type": "6M", "description": "Key VIP 6 tháng"},
  "TBTOOL_VIP_6M_A4B5C6D7": {"type": "6M", "description": "Key VIP 6 tháng"},
  "TBTOOL_VIP_6M_D7E8F9G1": {"type": "6M", "description": "Key VIP 6 tháng"},
  "TBTOOL_VIP_6M_G1H2I3J4": {"type": "6M", "description": "Key VIP 6 tháng"},
  "TBTOOL_VIP_6M_J4K5L6M7": {"type": "6M", "description": "Key VIP 6 tháng"},
  "TBTOOL_VIP_6M_M7N8O9P1": {"type": "6M", "description": "Key VIP 6 tháng"},
  "TBTOOL_VIP_6M_P1Q2R3S4": {"type": "6M", "description": "Key VIP 6 tháng"},
  "TBTOOL_VIP_6M_S4T5U6V7": {"type": "6M", "description": "Key VIP 6 tháng"},
  "TBTOOL_VIP_6M_V7W8X9Y1": {"type": "6M", "description": "Key VIP 6 tháng"},
  "TBTOOL_VIP_6M_Y1Z2A3B4": {"type": "6M", "description": "Key VIP 6 tháng"},
  "TBTOOL_VIP_6M_B4C5D6E7": {"type": "6M", "description": "Key VIP 6 tháng"},
  "TBTOOL_VIP_6M_E7F8G9H1": {"type": "6M", "description": "Key VIP 6 tháng"},
  "TBTOOL_VIP_6M_H1I2J3K4": {"type": "6M", "description": "Key VIP 6 tháng"},
  "TBTOOL_VIP_6M_K4L5M6N7": {"type": "6M", "description": "Key VIP 6 tháng"},
  "TBTOOL_VIP_6M_N7O8P9Q1": {"type": "6M", "description": "Key VIP 6 tháng"},
  "TBTOOL_VIP_6M_Q1R2S3T4": {"type": "6M", "description": "Key VIP 6 tháng"},
  "TBTOOL_VIP_6M_T4U5V6W7": {"type": "6M", "description": "Key VIP 6 tháng"},
  "TBTOOL_VIP_6M_W7X8Y9Z1": {"type": "6M", "description": "Key VIP 6 tháng"},
  "TBTOOL_VIP_6M_Z1A2B3C4": {"type": "6M", "description": "Key VIP 6 tháng"},
  "TBTOOL_VIP_6M_C4D5E6F7": {"type": "6M", "description": "Key VIP 6 tháng"},
  "TBTOOL_VIP_6M_F7G8H9I1": {"type": "6M", "description": "Key VIP 6 tháng"},
  "TBTOOL_VIP_6M_I1J2K3L4": {"type": "6M", "description": "Key VIP 6 tháng"},
  "TBTOOL_VIP_6M_L4M5N6O7": {"type": "6M", "description": "Key VIP 6 tháng"},
  "TBTOOL_VIP_6M_O7P8Q9R1": {"type": "6M", "description": "Key VIP 6 tháng"},
  "TBTOOL_VIP_6M_R1S2T3U4": {"type": "6M", "description": "Key VIP 6 tháng"},
  "TBTOOL_VIP_6M_U4V5W6X7": {"type": "6M", "description": "Key VIP 6 tháng"},
  "TBTOOL_VIP_6M_X7Y8Z9A1": {"type": "6M", "description": "Key VIP 6 tháng"},
  "TBTOOL_VIP_6M_A1B2C3D4": {"type": "6M", "description": "Key VIP 6 tháng"},
  "TBTOOL_VIP_6M_D4E5F6G7": {"type": "6M", "description": "Key VIP 6 tháng"},
  "TBTOOL_VIP_6M_G7H8I9J1": {"type": "6M", "description": "Key VIP 6 tháng"},
  "TBTOOL_VIP_6M_J1K2L3M4": {"type": "6M", "description": "Key VIP 6 tháng"},
  "TBTOOL_VIP_6M_M4N5O6P7": {"type": "6M", "description": "Key VIP 6 tháng"},
  "TBTOOL_VIP_6M_P7Q8R9S1": {"type": "6M", "description": "Key VIP 6 tháng"},
  "TBTOOL_VIP_6M_S1T2U3V4": {"type": "6M", "description": "Key VIP 6 tháng"},
  "TBTOOL_VIP_6M_V4W5X6Y7": {"type": "6M", "description": "Key VIP 6 tháng"},
  "TBTOOL_VIP_6M_Y7Z8A9B1": {"type": "6M", "description": "Key VIP 6 tháng"},
  "TBTOOL_VIP_6M_B1C2D3E4": {"type": "6M", "description": "Key VIP 6 tháng"},
  "TBTOOL_VIP_6M_E4F5G6H7": {"type": "6M", "description": "Key VIP 6 tháng"},
  "TBTOOL_VIP_6M_H7I8J9K1": {"type": "6M", "description": "Key VIP 6 tháng"},
  "TBTOOL_VIP_6M_K1L2M3N4": {"type": "6M", "description": "Key VIP 6 tháng"},
  "TBTOOL_VIP_6M_N4O5P6Q7": {"type": "6M", "description": "Key VIP 6 tháng"},
  "TBTOOL_VIP_6M_Q7R8S9T1": {"type": "6M", "description": "Key VIP 6 tháng"},
  "TBTOOL_VIP_6M_T1U2V3W4": {"type": "6M", "description": "Key VIP 6 tháng"},
  "TBTOOL_VIP_6M_W4X5Y6Z7": {"type": "6M", "description": "Key VIP 6 tháng"},
  "TBTOOL_VIP_6M_Z7A8B9C1": {"type": "6M", "description": "Key VIP 6 tháng"},
  "TBTOOL_VIP_6M_C1D2E3F4": {"type": "6M", "description": "Key VIP 6 tháng"},
  "TBTOOL_VIP_6M_F4G5H6I7": {"type": "6M", "description": "Key VIP 6 tháng"},
  "TBTOOL_VIP_6M_I7J8K9L1": {"type": "6M", "description": "Key VIP 6 tháng"},
  "TBTOOL_VIP_6M_L1M2N3O4": {"type": "6M", "description": "Key VIP 6 tháng"},
  "TBTOOL_VIP_6M_O4P5Q6R7": {"type": "6M", "description": "Key VIP 6 tháng"},
  "TBTOOL_VIP_6M_R7S8T9U1": {"type": "6M", "description": "Key VIP 6 tháng"},
  "TBTOOL_VIP_6M_U1V2W3X4": {"type": "6M", "description": "Key VIP 6 tháng"},
  "TBTOOL_VIP_6M_X4Y5Z6A7": {"type": "6M", "description": "Key VIP 6 tháng"},
  "TBTOOL_VIP_6M_A7B8C9D1": {"type": "6M", "description": "Key VIP 6 tháng"},
  "TBTOOL_VIP_6M_D1E2F3G4": {"type": "6M", "description": "Key VIP 6 tháng"},
  "TBTOOL_VIP_6M_G4H5I6J7": {"type": "6M", "description": "Key VIP 6 tháng"},
  "TBTOOL_VIP_6M_J7K8L9M1": {"type": "6M", "description": "Key VIP 6 tháng"},
  "TBTOOL_VIP_6M_M1N2O3P4": {"type": "6M", "description": "Key VIP 6 tháng"},
  "TBTOOL_VIP_6M_P4Q5R6S7": {"type": "6M", "description": "Key VIP 6 tháng"},
  "TBTOOL_VIP_6M_S7T8U9V1": {"type": "6M", "description": "Key VIP 6 tháng"},
  "TBTOOL_VIP_6M_V1W2X3Y4": {"type": "6M", "description": "Key VIP 6 tháng"},
  "TBTOOL_VIP_6M_Y4Z5A6B7": {"type": "6M", "description": "Key VIP 6 tháng"},
  "TBTOOL_VIP_6M_B7C8D9E1": {"type": "6M", "description": "Key VIP 6 tháng"},
  "TBTOOL_VIP_6M_E1F2G3H4": {"type": "6M", "description": "Key VIP 6 tháng"},
  "TBTOOL_VIP_6M_H4I5J6K7": {"type": "6M", "description": "Key VIP 6 tháng"},
  "TBTOOL_VIP_6M_K7L8M9N1": {"type": "6M", "description": "Key VIP 6 tháng"},
  "TBTOOL_VIP_6M_N1O2P3Q4": {"type": "6M", "description": "Key VIP 6 tháng"},
  "TBTOOL_VIP_6M_Q4R5S6T7": {"type": "6M", "description": "Key VIP 6 tháng"},
  "TBTOOL_VIP_6M_T7U8V9W1": {"type": "6M", "description": "Key VIP 6 tháng"},
  "TBTOOL_VIP_6M_W1X2Y3Z4": {"type": "6M", "description": "Key VIP 6 tháng"},
  "TBTOOL_VIP_6M_Z4A5B6C7": {"type": "6M", "description": "Key VIP 6 tháng"},

  "TBTOOL_VIP_1Y_W1X2Y3Z4": {"type": "1Y", "description": "Key VIP 1 năm"},
  "TBTOOL_VIP_1Y_Z4A5B6C7": {"type": "1Y", "description": "Key VIP 1 năm"},
  "TBTOOL_VIP_1Y_C7D8E9F1": {"type": "1Y", "description": "Key VIP 1 năm"},
  "TBTOOL_VIP_1Y_F1G2H3I4": {"type": "1Y", "description": "Key VIP 1 năm"},
  "TBTOOL_VIP_1Y_I4J5K6L7": {"type": "1Y", "description": "Key VIP 1 năm"},
  "TBTOOL_VIP_1Y_L7M8N9O1": {"type": "1Y", "description": "Key VIP 1 năm"},
  "TBTOOL_VIP_1Y_O1P2Q3R4": {"type": "1Y", "description": "Key VIP 1 năm"},
  "TBTOOL_VIP_1Y_R4S5T6U7": {"type": "1Y", "description": "Key VIP 1 năm"},
  "TBTOOL_VIP_1Y_U7V8W9X1": {"type": "1Y", "description": "Key VIP 1 năm"},
  "TBTOOL_VIP_1Y_X1Y2Z3A4": {"type": "1Y", "description": "Key VIP 1 năm"},
  "TBTOOL_VIP_1Y_A4B5C6D7": {"type": "1Y", "description": "Key VIP 1 năm"},
  "TBTOOL_VIP_1Y_D7E8F9G1": {"type": "1Y", "description": "Key VIP 1 năm"},
  "TBTOOL_VIP_1Y_G1H2I3J4": {"type": "1Y", "description": "Key VIP 1 năm"},
  "TBTOOL_VIP_1Y_J4K5L6M7": {"type": "1Y", "description": "Key VIP 1 năm"},
  "TBTOOL_VIP_1Y_M7N8O9P1": {"type": "1Y", "description": "Key VIP 1 năm"},
  "TBTOOL_VIP_1Y_P1Q2R3S4": {"type": "1Y", "description": "Key VIP 1 năm"},
  "TBTOOL_VIP_1Y_S4T5U6V7": {"type": "1Y", "description": "Key VIP 1 năm"},
  "TBTOOL_VIP_1Y_V7W8X9Y1": {"type": "1Y", "description": "Key VIP 1 năm"},
  "TBTOOL_VIP_1Y_Y1Z2A3B4": {"type": "1Y", "description": "Key VIP 1 năm"},
  "TBTOOL_VIP_1Y_B4C5D6E7": {"type": "1Y", "description": "Key VIP 1 năm"},
  "TBTOOL_VIP_1Y_E7F8G9H1": {"type": "1Y", "description": "Key VIP 1 năm"},
  "TBTOOL_VIP_1Y_H1I2J3K4": {"type": "1Y", "description": "Key VIP 1 năm"},
  "TBTOOL_VIP_1Y_K4L5M6N7": {"type": "1Y", "description": "Key VIP 1 năm"},
  "TBTOOL_VIP_1Y_N7O8P9Q1": {"type": "1Y", "description": "Key VIP 1 năm"},
  "TBTOOL_VIP_1Y_Q1R2S3T4": {"type": "1Y", "description": "Key VIP 1 năm"},
  "TBTOOL_VIP_1Y_T4U5V6W7": {"type": "1Y", "description": "Key VIP 1 năm"},
  "TBTOOL_VIP_1Y_W7X8Y9Z1": {"type": "1Y", "description": "Key VIP 1 năm"},
  "TBTOOL_VIP_1Y_Z1A2B3C4": {"type": "1Y", "description": "Key VIP 1 năm"},
  "TBTOOL_VIP_1Y_C4D5E6F7": {"type": "1Y", "description": "Key VIP 1 năm"},
  "TBTOOL_VIP_1Y_F7G8H9I1": {"type": "1Y", "description": "Key VIP 1 năm"},
  "TBTOOL_VIP_1Y_I1J2K3L4": {"type": "1Y", "description": "Key VIP 1 năm"},
  "TBTOOL_VIP_1Y_L4M5N6O7": {"type": "1Y", "description": "Key VIP 1 năm"},
  "TBTOOL_VIP_1Y_O7P8Q9R1": {"type": "1Y", "description": "Key VIP 1 năm"},
  "TBTOOL_VIP_1Y_R1S2T3U4": {"type": "1Y", "description": "Key VIP 1 năm"},
  "TBTOOL_VIP_1Y_U4V5W6X7": {"type": "1Y", "description": "Key VIP 1 năm"},
  "TBTOOL_VIP_1Y_X7Y8Z9A1": {"type": "1Y", "description": "Key VIP 1 năm"},
  "TBTOOL_VIP_1Y_A1B2C3D4": {"type": "1Y", "description": "Key VIP 1 năm"},
  "TBTOOL_VIP_1Y_D4E5F6G7": {"type": "1Y", "description": "Key VIP 1 năm"},
  "TBTOOL_VIP_1Y_G7H8I9J1": {"type": "1Y", "description": "Key VIP 1 năm"},
  "TBTOOL_VIP_1Y_J1K2L3M4": {"type": "1Y", "description": "Key VIP 1 năm"},
  "TBTOOL_VIP_1Y_M4N5O6P7": {"type": "1Y", "description": "Key VIP 1 năm"},
  "TBTOOL_VIP_1Y_P7Q8R9S1": {"type": "1Y", "description": "Key VIP 1 năm"},
  "TBTOOL_VIP_1Y_S1T2U3V4": {"type": "1Y", "description": "Key VIP 1 năm"},
  "TBTOOL_VIP_1Y_V4W5X6Y7": {"type": "1Y", "description": "Key VIP 1 năm"},
  "TBTOOL_VIP_1Y_Y7Z8A9B1": {"type": "1Y", "description": "Key VIP 1 năm"},
  "TBTOOL_VIP_1Y_B1C2D3E4": {"type": "1Y", "description": "Key VIP 1 năm"},
  "TBTOOL_VIP_1Y_E4F5G6H7": {"type": "1Y", "description": "Key VIP 1 năm"},
  "TBTOOL_VIP_1Y_H7I8J9K1": {"type": "1Y", "description": "Key VIP 1 năm"},
  "TBTOOL_VIP_1Y_K1L2M3N4": {"type": "1Y", "description": "Key VIP 1 năm"},
  "TBTOOL_VIP_1Y_N4O5P6Q7": {"type": "1Y", "description": "Key VIP 1 năm"},
  "TBTOOL_VIP_1Y_Q7R8S9T1": {"type": "1Y", "description": "Key VIP 1 năm"},
  "TBTOOL_VIP_1Y_T1U2V3W4": {"type": "1Y", "description": "Key VIP 1 năm"},
  "TBTOOL_VIP_1Y_W4X5Y6Z7": {"type": "1Y", "description": "Key VIP 1 năm"},
  "TBTOOL_VIP_1Y_Z7A8B9C1": {"type": "1Y", "description": "Key VIP 1 năm"},
  "TBTOOL_VIP_1Y_C1D2E3F4": {"type": "1Y", "description": "Key VIP 1 năm"},
  "TBTOOL_VIP_1Y_F4G5H6I7": {"type": "1Y", "description": "Key VIP 1 năm"},
  "TBTOOL_VIP_1Y_I7J8K9L1": {"type": "1Y", "description": "Key VIP 1 năm"},
  "TBTOOL_VIP_1Y_L1M2N3O4": {"type": "1Y", "description": "Key VIP 1 năm"},
  "TBTOOL_VIP_1Y_O4P5Q6R7": {"type": "1Y", "description": "Key VIP 1 năm"},
  "TBTOOL_VIP_1Y_R7S8T9U1": {"type": "1Y", "description": "Key VIP 1 năm"},
  "TBTOOL_VIP_1Y_U1V2W3X4": {"type": "1Y", "description": "Key VIP 1 năm"},
  "TBTOOL_VIP_1Y_X4Y5Z6A7": {"type": "1Y", "description": "Key VIP 1 năm"},
  "TBTOOL_VIP_1Y_A7B8C9D1": {"type": "1Y", "description": "Key VIP 1 năm"},
  "TBTOOL_VIP_1Y_D1E2F3G4": {"type": "1Y", "description": "Key VIP 1 năm"},
  "TBTOOL_VIP_1Y_G4H5I6J7": {"type": "1Y", "description": "Key VIP 1 năm"},
  "TBTOOL_VIP_1Y_J7K8L9M1": {"type": "1Y", "description": "Key VIP 1 năm"},
  "TBTOOL_VIP_1Y_M1N2O3P4": {"type": "1Y", "description": "Key VIP 1 năm"},
  "TBTOOL_VIP_1Y_P4Q5R6S7": {"type": "1Y", "description": "Key VIP 1 năm"},
  "TBTOOL_VIP_1Y_S7T8U9V1": {"type": "1Y", "description": "Key VIP 1 năm"},
  "TBTOOL_VIP_1Y_V1W2X3Y4": {"type": "1Y", "description": "Key VIP 1 năm"},
  "TBTOOL_VIP_1Y_Y4Z5A6B7": {"type": "1Y", "description": "Key VIP 1 năm"},
  "TBTOOL_VIP_1Y_B7C8D9E1": {"type": "1Y", "description": "Key VIP 1 năm"},
  "TBTOOL_VIP_1Y_E1F2G3H4": {"type": "1Y", "description": "Key VIP 1 năm"},
  "TBTOOL_VIP_1Y_H4I5J6K7": {"type": "1Y", "description": "Key VIP 1 năm"},
  "TBTOOL_VIP_1Y_K7L8M9N1": {"type": "1Y", "description": "Key VIP 1 năm"},
  "TBTOOL_VIP_1Y_N1O2P3Q4": {"type": "1Y", "description": "Key VIP 1 năm"},
  "TBTOOL_VIP_1Y_Q4R5S6T7": {"type": "1Y", "description": "Key VIP 1 năm"},
  "TBTOOL_VIP_1Y_T7U8V9W1": {"type": "1Y", "description": "Key VIP 1 năm"},
  "TBTOOL_VIP_1Y_W1X2Y3Z4": {"type": "1Y", "description": "Key VIP 1 năm"},
  "TBTOOL_VIP_1Y_Z4A5B6C7": {"type": "1Y", "description": "Key VIP 1 năm"},
  "TBTOOL_VIP_1Y_C7D8E9F1": {"type": "1Y", "description": "Key VIP 1 năm"},
  "TBTOOL_VIP_1Y_F1G2H3I4": {"type": "1Y", "description": "Key VIP 1 năm"},
  "TBTOOL_VIP_1Y_I4J5K6L7": {"type": "1Y", "description": "Key VIP 1 năm"},
  "TBTOOL_VIP_1Y_L7M8N9O1": {"type": "1Y", "description": "Key VIP 1 năm"},
  "TBTOOL_VIP_1Y_O1P2Q3R4": {"type": "1Y", "description": "Key VIP 1 năm"},
  "TBTOOL_VIP_1Y_R4S5T6U7": {"type": "1Y", "description": "Key VIP 1 năm"},
  "TBTOOL_VIP_1Y_U7V8W9X1": {"type": "1Y", "description": "Key VIP 1 năm"},
  "TBTOOL_VIP_1Y_X1Y2Z3A4": {"type": "1Y", "description": "Key VIP 1 năm"},
  "TBTOOL_VIP_1Y_A4B5C6D7": {"type": "1Y", "description": "Key VIP 1 năm"},
  "TBTOOL_VIP_1Y_D7E8F9G1": {"type": "1Y", "description": "Key VIP 1 năm"},
  "TBTOOL_VIP_1Y_G1H2I3J4": {"type": "1Y", "description": "Key VIP 1 năm"},
  "TBTOOL_VIP_1Y_J4K5L6M7": {"type": "1Y", "description": "Key VIP 1 năm"},
  "TBTOOL_VIP_1Y_M7N8O9P1": {"type": "1Y", "description": "Key VIP 1 năm"},
  "TBTOOL_VIP_1Y_P1Q2R3S4": {"type": "1Y", "description": "Key VIP 1 năm"},
  "TBTOOL_VIP_1Y_S4T5U6V7": {"type": "1Y", "description": "Key VIP 1 năm"},
  "TBTOOL_VIP_1Y_V7W8X9Y1": {"type": "1Y", "description": "Key VIP 1 năm"},
  "TBTOOL_VIP_1Y_Y1Z2A3B4": {"type": "1Y", "description": "Key VIP 1 năm"},
  "TBTOOL_VIP_1Y_B4C5D6E7": {"type": "1Y", "description": "Key VIP 1 năm"},
  "TBTOOL_VIP_1Y_E7F8G9H1": {"type": "1Y", "description": "Key VIP 1 năm"},
  "TBTOOL_VIP_1Y_H1I2J3K4": {"type": "1Y", "description": "Key VIP 1 năm"},
  "TBTOOL_VIP_1Y_K4L5M6N7": {"type": "1Y", "description": "Key VIP 1 năm"},
  "TBTOOL_VIP_1Y_N7O8P9Q1": {"type": "1Y", "description": "Key VIP 1 năm"},
  "TBTOOL_VIP_1Y_Q1R2S3T4": {"type": "1Y", "description": "Key VIP 1 năm"},

  "TBTOOL_VIP_VV_001A": {"type": "VV", "description": "Key VIP Vĩnh Viễn"},
  "TBTOOL_VIP_VV_002B": {"type": "VV", "description": "Key VIP Vĩnh Viễn"},
  "TBTOOL_VIP_VV_003C": {"type": "VV", "description": "Key VIP Vĩnh Viễn"},
  "TBTOOL_VIP_VV_004D": {"type": "VV", "description": "Key VIP Vĩnh Viễn"},
  "TBTOOL_VIP_VV_005E": {"type": "VV", "description": "Key VIP Vĩnh Viễn"},
  "TBTOOL_VIP_VV_006F": {"type": "VV", "description": "Key VIP Vĩnh Viễn"},
  "TBTOOL_VIP_VV_007G": {"type": "VV", "description": "Key VIP Vĩnh Viễn"},
  "TBTOOL_VIP_VV_008H": {"type": "VV", "description": "Key VIP Vĩnh Viễn"},
  "TBTOOL_VIP_VV_009I": {"type": "VV", "description": "Key VIP Vĩnh Viễn"},
  "TBTOOL_VIP_VV_010J": {"type": "VV", "description": "Key VIP Vĩnh Viễn"},
  "TBTOOL_VIP_VV_011K": {"type": "VV", "description": "Key VIP Vĩnh Viễn"},
  "TBTOOL_VIP_VV_012L": {"type": "VV", "description": "Key VIP Vĩnh Viễn"},
  "TBTOOL_VIP_VV_013M": {"type": "VV", "description": "Key VIP Vĩnh Viễn"},
  "TBTOOL_VIP_VV_014N": {"type": "VV", "description": "Key VIP Vĩnh Viễn"},
  "TBTOOL_VIP_VV_015O": {"type": "VV", "description": "Key VIP Vĩnh Viễn"},
  "TBTOOL_VIP_VV_016P": {"type": "VV", "description": "Key VIP Vĩnh Viễn"},
  "TBTOOL_VIP_VV_017Q": {"type": "VV", "description": "Key VIP Vĩnh Viễn"},
  "TBTOOL_VIP_VV_018R": {"type": "VV", "description": "Key VIP Vĩnh Viễn"},
  "TBTOOL_VIP_VV_019S": {"type": "VV", "description": "Key VIP Vĩnh Viễn"},
  "TBTOOL_VIP_VV_020T": {"type": "VV", "description": "Key VIP Vĩnh Viễn"},
  "TBTOOL_VIP_VV_021U": {"type": "VV", "description": "Key VIP Vĩnh Viễn"},
  "TBTOOL_VIP_VV_022V": {"type": "VV", "description": "Key VIP Vĩnh Viễn"},
  "TBTOOL_VIP_VV_023W": {"type": "VV", "description": "Key VIP Vĩnh Viễn"},
  "TBTOOL_VIP_VV_024X": {"type": "VV", "description": "Key VIP Vĩnh Viễn"},
  "TBTOOL_VIP_VV_025Y": {"type": "VV", "description": "Key VIP Vĩnh Viễn"},
  "TBTOOL_VIP_VV_026Z": {"type": "VV", "description": "Key VIP Vĩnh Viễn"},
  "TBTOOL_VIP_VV_027A": {"type": "VV", "description": "Key VIP Vĩnh Viễn"},
  "TBTOOL_VIP_VV_028B": {"type": "VV", "description": "Key VIP Vĩnh Viễn"},
  "TBTOOL_VIP_VV_029C": {"type": "VV", "description": "Key VIP Vĩnh Viễn"},
  "TBTOOL_VIP_VV_030D": {"type": "VV", "description": "Key VIP Vĩnh Viễn"},
  "TBTOOL_VIP_VV_031E": {"type": "VV", "description": "Key VIP Vĩnh Viễn"},
  "TBTOOL_VIP_VV_032F": {"type": "VV", "description": "Key VIP Vĩnh Viễn"},
  "TBTOOL_VIP_VV_033G": {"type": "VV", "description": "Key VIP Vĩnh Viễn"},
  "TBTOOL_VIP_VV_034H": {"type": "VV", "description": "Key VIP Vĩnh Viễn"},
  "TBTOOL_VIP_VV_035I": {"type": "VV", "description": "Key VIP Vĩnh Viễn"},
  "TBTOOL_VIP_VV_036J": {"type": "VV", "description": "Key VIP Vĩnh Viễn"},
  "TBTOOL_VIP_VV_037K": {"type": "VV", "description": "Key VIP Vĩnh Viễn"},
  "TBTOOL_VIP_VV_038L": {"type": "VV", "description": "Key VIP Vĩnh Viễn"},
  "TBTOOL_VIP_VV_039M": {"type": "VV", "description": "Key VIP Vĩnh Viễn"},
  "TBTOOL_VIP_VV_040N": {"type": "VV", "description": "Key VIP Vĩnh Viễn"},
  "TBTOOL_VIP_VV_041O": {"type": "VV", "description": "Key VIP Vĩnh Viễn"},
  "TBTOOL_VIP_VV_042P": {"type": "VV", "description": "Key VIP Vĩnh Viễn"},
  "TBTOOL_VIP_VV_043Q": {"type": "VV", "description": "Key VIP Vĩnh Viễn"},
  "TBTOOL_VIP_VV_044R": {"type": "VV", "description": "Key VIP Vĩnh Viễn"},
  "TBTOOL_VIP_VV_045S": {"type": "VV", "description": "Key VIP Vĩnh Viễn"},
  "TBTOOL_VIP_VV_046T": {"type": "VV", "description": "Key VIP Vĩnh Viễn"},
  "TBTOOL_VIP_VV_047U": {"type": "VV", "description": "Key VIP Vĩnh Viễn"},
  "TBTOOL_VIP_VV_048V": {"type": "VV", "description": "Key VIP Vĩnh Viễn"},
  "TBTOOL_VIP_VV_049W": {"type": "VV", "description": "Key VIP Vĩnh Viễn"},
  "TBTOOL_VIP_VV_050X": {"type": "VV", "description": "Key VIP Vĩnh Viễn"},
  "TBTOOL_VIP_VV_051Y": {"type": "VV", "description": "Key VIP Vĩnh Viễn"},
  "TBTOOL_VIP_VV_052Z": {"type": "VV", "description": "Key VIP Vĩnh Viễn"},
  "TBTOOL_VIP_VV_053A": {"type": "VV", "description": "Key VIP Vĩnh Viễn"},
  "TBTOOL_VIP_VV_054B": {"type": "VV", "description": "Key VIP Vĩnh Viễn"},
  "TBTOOL_VIP_VV_055C": {"type": "VV", "description": "Key VIP Vĩnh Viễn"},
  "TBTOOL_VIP_VV_056D": {"type": "VV", "description": "Key VIP Vĩnh Viễn"},
  "TBTOOL_VIP_VV_057E": {"type": "VV", "description": "Key VIP Vĩnh Viễn"},
  "TBTOOL_VIP_VV_058F": {"type": "VV", "description": "Key VIP Vĩnh Viễn"},
  "TBTOOL_VIP_VV_059G": {"type": "VV", "description": "Key VIP Vĩnh Viễn"},
  "TBTOOL_VIP_VV_060H": {"type": "VV", "description": "Key VIP Vĩnh Viễn"},
  "TBTOOL_VIP_VV_061I": {"type": "VV", "description": "Key VIP Vĩnh Viễn"},
  "TBTOOL_VIP_VV_062J": {"type": "VV", "description": "Key VIP Vĩnh Viễn"},
  "TBTOOL_VIP_VV_063K": {"type": "VV", "description": "Key VIP Vĩnh Viễn"},
  "TBTOOL_VIP_VV_064L": {"type": "VV", "description": "Key VIP Vĩnh Viễn"},
  "TBTOOL_VIP_VV_065M": {"type": "VV", "description": "Key VIP Vĩnh Viễn"},
  "TBTOOL_VIP_VV_066N": {"type": "VV", "description": "Key VIP Vĩnh Viễn"},
  "TBTOOL_VIP_VV_067O": {"type": "VV", "description": "Key VIP Vĩnh Viễn"},
  "TBTOOL_VIP_VV_068P": {"type": "VV", "description": "Key VIP Vĩnh Viễn"},
  "TBTOOL_VIP_VV_069Q": {"type": "VV", "description": "Key VIP Vĩnh Viễn"},
  "TBTOOL_VIP_VV_070R": {"type": "VV", "description": "Key VIP Vĩnh Viễn"},
  "TBTOOL_VIP_VV_071S": {"type": "VV", "description": "Key VIP Vĩnh Viễn"},
  "TBTOOL_VIP_VV_072T": {"type": "VV", "description": "Key VIP Vĩnh Viễn"},
  "TBTOOL_VIP_VV_073U": {"type": "VV", "description": "Key VIP Vĩnh Viễn"},
  "TBTOOL_VIP_VV_074V": {"type": "VV", "description": "Key VIP Vĩnh Viễn"},
  "TBTOOL_VIP_VV_075W": {"type": "VV", "description": "Key VIP Vĩnh Viễn"},
  "TBTOOL_VIP_VV_076X": {"type": "VV", "description": "Key VIP Vĩnh Viễn"},
  "TBTOOL_VIP_VV_077Y": {"type": "VV", "description": "Key VIP Vĩnh Viễn"},
  "TBTOOL_VIP_VV_078Z": {"type": "VV", "description": "Key VIP Vĩnh Viễn"},
  "TBTOOL_VIP_VV_079A": {"type": "VV", "description": "Key VIP Vĩnh Viễn"},
  "TBTOOL_VIP_VV_080B": {"type": "VV", "description": "Key VIP Vĩnh Viễn"},
  "TBTOOL_VIP_VV_081C": {"type": "VV", "description": "Key VIP Vĩnh Viễn"},
  "TBTOOL_VIP_VV_082D": {"type": "VV", "description": "Key VIP Vĩnh Viễn"},
  "TBTOOL_VIP_VV_083E": {"type": "VV", "description": "Key VIP Vĩnh Viễn"},
  "TBTOOL_VIP_VV_084F": {"type": "VV", "description": "Key VIP Vĩnh Viễn"},
  "TBTOOL_VIP_VV_085G": {"type": "VV", "description": "Key VIP Vĩnh Viễn"},
  "TBTOOL_VIP_VV_086H": {"type": "VV", "description": "Key VIP Vĩnh Viễn"},
  "TBTOOL_VIP_VV_087I": {"type": "VV", "description": "Key VIP Vĩnh Viễn"},
  "TBTOOL_VIP_VV_088J": {"type": "VV", "description": "Key VIP Vĩnh Viễn"},
  "TBTOOL_VIP_VV_089K": {"type": "VV", "description": "Key VIP Vĩnh Viễn"},
  "TBTOOL_VIP_VV_090L": {"type": "VV", "description": "Key VIP Vĩnh Viễn"},
  "TBTOOL_VIP_VV_091M": {"type": "VV", "description": "Key VIP Vĩnh Viễn"},
  "TBTOOL_VIP_VV_092N": {"type": "VV", "description": "Key VIP Vĩnh Viễn"},
  "TBTOOL_VIP_VV_093O": {"type": "VV", "description": "Key VIP Vĩnh Viễn"},
  "TBTOOL_VIP_VV_094P": {"type": "VV", "description": "Key VIP Vĩnh Viễn"},
  "TBTOOL_VIP_VV_095Q": {"type": "VV", "description": "Key VIP Vĩnh Viễn"},
  "TBTOOL_VIP_VV_096R": {"type": "VV", "description": "Key VIP Vĩnh Viễn"},
  "TBTOOL_VIP_VV_097S": {"type": "VV", "description": "Key VIP Vĩnh Viễn"},
  "TBTOOL_VIP_VV_098T": {"type": "VV", "description": "Key VIP Vĩnh Viễn"},
  "TBTOOL_VIP_VV_099U": {"type": "VV", "description": "Key VIP Vĩnh Viễn"},
  "TBTOOL_VIP_VV_100V": {"type": "VV", "description": "Key VIP Vĩnh Viễn"}
}
